Workbook

Sheet README
B2: CBO's Sanctions Penalty Model
B3: Posted 2026-02-24
B4: https://github.com/US-CBO/sanctions-penalty-model
B6: What This Model Does
B7: This model projects penalty revenues from civil settlements for violations of various sanctions for CBO's revenue baseline.
B9: Background
B10: The Department of Treasury’s Office of Foreign Assets Control (OFAC) administers and enforces economic sanctions. These sanctions prohibit people and
B11: organizations operating under U.S. jurisdiction from engaging in transactions with certain foreign actors
B13: This model tracks settlements, dating back to 2011, and uses those historic data to project future revenues from civil settlements. The model also
B14: incorporates adjustments for recent changes in sanctions that are not reflected in historic data.
B16: Projection Strategy
B17: 1. Gather settlement data from agreements released on OFAC’s ‘Enforcement Actions’ page. | K17: (https://ofac.treasury.gov/recent-actions/enforcement-actions)
B18: 2. For any historic penalties associated with violations of multiple sanctions, assign a share of that penalty to each type of sanction violated.
B19: 3. Calculate the average settlement over the past 10 years for each type of sanction violation.
B20: 4. Project revenues from 2026-2036 by growing that historical average by CBO’s projected growth of the Consumer Price Index for All Urban Consumers (CPI-U).
B21: 5. Adjust to account for an anticipated increase in settlements for violations related to Russia, arising from expanded sanctions on various Russian citizens
B22: and industries following the 2022 invasion of Ukraine, which are not reflected in historical sett
B23: 6. Sum projections from sanctions programs, along with the Russian adjustment, to calculate total projected revenues over the 2026-2036 period.
B25: Table of Contents
B26: Summary: Displays total projected revenue from civil settlements of sanctions violations over the 2026-2036 period.
B27: Fiscal Year Projections: Projects revenues from civil settlements across all sanctions programs across the 2026-2036 period.
B28: Adjusted Russia Projections: An adjustment to account for expanded sanctions on various Russian citizens and industries following the 2022 invasion of Ukraine
B29: Country-Specific Data: Sums announced settlements from active country-specific sanctions programs (that is, violations of sanctions on certain countries’
B30: citizens, governments, and entities)
... B53: The sanctions penalty model was developed by Emma Uebelhor, Madeleine Fox (formally of CBO), and Jacob Fabian (formally of CBO).

Sheet Summary
A1: Fiscal Year | B1: 2026 | C1: 2027 | D1: 2028 | E1: 2029 | F1: 2030 | G1: 2031 | H1: 2032 | I1: 2033 | J1: 2034 | K1: 2035 | L1: 2036 | M1: 2026-2036
A2: millions of dollars
A4: Projected Revenue | B4: ='Fiscal Year Projections'!Q37/1000000 -> 256.308 | C4: ='Fiscal Year Projections'!R37/1000000 -> 263.084 | D4: ='Fiscal Year Projections'!S37/1000000 -> 269.36932 | E4: ='Fiscal Year Projections'!T37/1000000 -> 716.52914 | F4: ='Fiscal Year Projections'!U37/1000000 -> 732.76966 | G4: ='Fiscal Year Projections'!V37/1000000 -> 749.32683 | H4: ='Fiscal Year Projections'!W37/1000000 -> 766.24304 | I4: ='Fiscal Year Projections'!X37/1000000 -> 783.53495 | ... L4: ='Fiscal Year Projections'!AA37/1000000 -> 837.79366 | M4: =SUM(B4:L4) -> 6995.4738

Sheet Fiscal Year Projections
A1: Fiscal Year | B1: 2011 | C1: 2012 | D1: 2013 | E1: 2014 | F1: 2015 | G1: 2016 | H1: 2017 | I1: 2018 | J1: 2019 | K1: 2020 | L1: 2021 | M1: 2022 | N1: 2023 | O1: 2024 | P1: 2025 | Q1: 2026 | R1: 2027 | S1: 2028 | T1: 2029 | U1: 2030 | V1: 2031 | W1: 2032 | X1: 2033 | Y1: 2034 | Z1: 2035 | AA1: 2036
A3: CBO's Projected Consumer Price Index for All Urban Consumers (CPI-U) | B3: 2.2308592 | C3: 2.2850558 | D3: 2.3225342 | E3: 2.3603358 | F3: 2.3676458 | G3: 2.38931 | H3: 2.4384508 | I3: 2.4973133 | J3: 2.5435833 | K3: 2.5805483 | L3: 2.66561 | M3: 2.8768067 | N3: 3.0228917 | O3: 3.1160275 | P3: 3.2002975 | Q3: 3.2950815 | R3: 3.3821934 | S3: 3.4629972 | T3: 3.5426797 | U3: 3.6229765 | V3: 3.7048388 | W3: 3.7884763 | X3: 3.8739714 | Y3: 3.9613918 | Z3: 4.0507964 | AA3: 4.1422385
A4: Rate | C4: =C3/B3 -> 1.0242941 | D4: =D3/C3 -> 1.0164015 | E4: =E3/D3 -> 1.016276 | F4: =F3/E3 -> 1.003097 | G4: =G3/F3 -> 1.0091501 | H4: =H3/G3 -> 1.020567 | I4: =I3/H3 -> 1.0241393 | J4: =J3/I3 -> 1.0185279 | ... AA4: =AA3/Z3 -> 1.0225739
A7: Country Projections
A8: Afghanistan | B8: ='Country-Specific Data'!B3 -> 0 | C8: ='Country-Specific Data'!C3 -> 0 | D8: ='Country-Specific Data'!D3 -> 0 | E8: ='Country-Specific Data'!E3 -> 0 | F8: ='Country-Specific Data'!F3 -> 0 | G8: ='Country-Specific Data'!G3 -> 0 | H8: ='Country-Specific Data'!H3 -> 0 | I8: ='Country-Specific Data'!I3 -> 0 | ... P8: ='Country-Specific Data'!P3 -> 0 | Q8: =AVERAGE(G8:P8)*Q$4 -> 0 | R8: =Q8*R$4 -> 0 | S8: =R8*S$4 -> 0 | T8: =S8*T$4 -> 0 | U8: =T8*U$4 -> 0 | V8: =U8*V$4 -> 0 | W8: =V8*W$4 -> 0 | X8: =W8*X$4 -> 0 | Y8: =X8*Y$4 -> 0 | ... AA8: =Z8*AA$4 -> 0
A9: Belarus | B9: ='Country-Specific Data'!B4 -> 0 | C9: ='Country-Specific Data'!C4 -> 0 | D9: ='Country-Specific Data'!D4 -> 0 | E9: ='Country-Specific Data'!E4 -> 0 | F9: ='Country-Specific Data'!F4 -> 0 | G9: ='Country-Specific Data'!G4 -> 0 | H9: ='Country-Specific Data'!H4 -> 0 | I9: ='Country-Specific Data'!I4 -> 0 | ... P9: ='Country-Specific Data'!P4 -> 0 | Q9: =AVERAGE(G9:P9)*Q$4 -> 800229.03 | R9: =Q9*R$4 -> 821384.64 | S9: =R9*S$4 -> 841008.28 | T9: =S9*T$4 -> 860359.64 | U9: =T9*U$4 -> 879860.16 | V9: =U9*V$4 -> 899740.89 | W9: =V9*W$4 -> 920052.73 | X9: =W9*X$4 -> 940815.69 | Y9: =X9*Y$4 -> 962046.22 | ... AA9: =Z9*AA$4 -> 1005965.9
A10: Burma | B10: ='Country-Specific Data'!B5 -> 0 | C10: ='Country-Specific Data'!C5 -> 18514021 | D10: ='Country-Specific Data'!D5 -> 1.3671728e+08 | E10: ='Country-Specific Data'!E5 -> 3082289.4 | F10: ='Country-Specific Data'!F5 -> 8925835.9 | G10: ='Country-Specific Data'!G5 -> 5231994.3 | H10: ='Country-Specific Data'!H5 -> 0 | I10: ='Country-Specific Data'!I5 -> 0 | ... P10: ='Country-Specific Data'!P5 -> 0 | Q10: =AVERAGE(G10:P10)*Q$4 -> 790401.51 | R10: =Q10*R$4 -> 811297.32 | S10: =R10*S$4 -> 830679.96 | T10: =S10*T$4 -> 849793.67 | U10: =T10*U$4 -> 869054.7 | V10: =U10*V$4 -> 888691.28 | W10: =V10*W$4 -> 908753.67 | X10: =W10*X$4 -> 929261.64 | Y10: =X10*Y$4 -> 950231.44 | ... AA10: =Z10*AA$4 -> 993611.72
A11: Central African Republic | B11: ='Country-Specific Data'!B6 -> 0 | C11: ='Country-Specific Data'!C6 -> 0 | D11: ='Country-Specific Data'!D6 -> 0 | E11: ='Country-Specific Data'!E6 -> 0 | F11: ='Country-Specific Data'!F6 -> 0 | G11: ='Country-Specific Data'!G6 -> 0 | H11: ='Country-Specific Data'!H6 -> 0 | I11: ='Country-Specific Data'!I6 -> 0 | ... P11: ='Country-Specific Data'!P6 -> 0 | Q11: =AVERAGE(G11:P11)*Q$4 -> 589.09174 | R11: =Q11*R$4 -> 604.66552 | S11: =R11*S$4 -> 619.11154 | T11: =S11*T$4 -> 633.35712 | U11: =T11*U$4 -> 647.7125 | V11: =U11*V$4 -> 662.34778 | W11: =V11*W$4 -> 677.30042 | X11: =W11*X$4 -> 692.58515 | Y11: =X11*Y$4 -> 708.21409 | ... AA11: =Z11*AA$4 -> 740.54571
A12: Cuba | B12: ='Country-Specific Data'!B7 -> 86344238 | C12: ='Country-Specific Data'!C7 -> 5.9306532e+08 | D12: ='Country-Specific Data'!D7 -> 8508305.9 | E12: ='Country-Specific Data'!E7 -> 80845798 | F12: ='Country-Specific Data'!F7 -> 3714101.4 | G12: ='Country-Specific Data'!G7 -> 3633356 | H12: ='Country-Specific Data'!H7 -> 1069620.1 | I12: ='Country-Specific Data'!I7 -> 204277 | ... P12: ='Country-Specific Data'!P7 -> 925170 | Q12: =AVERAGE(G12:P12)*Q$4 -> 9029589 | R12: =Q12*R$4 -> 9268303.8 | S12: =R12*S$4 -> 9489732.1 | T12: =S12*T$4 -> 9708088.1 | U12: =T12*U$4 -> 9928127.2 | V12: =U12*V$4 -> 10152457 | W12: =V12*W$4 -> 10381650 | X12: =W12*X$4 -> 10615934 | Y12: =X12*Y$4 -> 10855495 | ... AA12: =Z12*AA$4 -> 11351073
A13: Democratic Republic of the Congo | B13: ='Country-Specific Data'!B8 -> 0 | C13: ='Country-Specific Data'!C8 -> 0 | D13: ='Country-Specific Data'!D8 -> 0 | E13: ='Country-Specific Data'!E8 -> 0 | F13: ='Country-Specific Data'!F8 -> 0 | G13: ='Country-Specific Data'!G8 -> 0 | H13: ='Country-Specific Data'!H8 -> 0 | I13: ='Country-Specific Data'!I8 -> 0 | ... P13: ='Country-Specific Data'!P8 -> 0 | Q13: =AVERAGE(G13:P13)*Q$4 -> 589.09174 | R13: =Q13*R$4 -> 604.66552 | S13: =R13*S$4 -> 619.11154 | T13: =S13*T$4 -> 633.35712 | U13: =T13*U$4 -> 647.7125 | V13: =U13*V$4 -> 662.34778 | W13: =V13*W$4 -> 677.30042 | X13: =W13*X$4 -> 692.58515 | Y13: =X13*Y$4 -> 708.21409 | ... AA13: =Z13*AA$4 -> 740.54571
A14: Ethopia | B14: ='Country-Specific Data'!B9 -> 0 | C14: ='Country-Specific Data'!C9 -> 0 | D14: ='Country-Specific Data'!D9 -> 0 | E14: ='Country-Specific Data'!E9 -> 0 | F14: ='Country-Specific Data'!F9 -> 0 | G14: ='Country-Specific Data'!G9 -> 0 | H14: ='Country-Specific Data'!H9 -> 0 | I14: ='Country-Specific Data'!I9 -> 0 | ... P14: ='Country-Specific Data'!P9 -> 0 | Q14: =AVERAGE(G14:P14)*Q$4 -> 0 | R14: =Q14*R$4 -> 0 | S14: =R14*S$4 -> 0 | T14: =S14*T$4 -> 0 | U14: =T14*U$4 -> 0 | V14: =U14*V$4 -> 0 | W14: =V14*W$4 -> 0 | X14: =W14*X$4 -> 0 | Y14: =X14*Y$4 -> 0 | ... AA14: =Z14*AA$4 -> 0
A15: Iran | B15: ='Country-Specific Data'!B10 -> 729194.33 | C15: ='Country-Specific Data'!C10 -> 6150319 | D15: ='Country-Specific Data'!D10 -> 1.6640826e+08 | E15: ='Country-Specific Data'!E10 -> 3.2276752e+08 | F15: ='Country-Specific Data'!F10 -> 1.0897463e+08 | G15: ='Country-Specific Data'!G10 -> 9394493 | H15: ='Country-Specific Data'!H10 -> 1.2023835e+08 | I15: ='Country-Specific Data'!I10 -> 2720400 | ... P15: ='Country-Specific Data'!P10 -> 17833143 | Q15: =AVERAGE(G15:P15)*Q$4 -> 1.1414786e+08 | R15: =Q15*R$4 -> 1.1716558e+08 | S15: =R15*S$4 -> 1.1996477e+08 | T15: =S15*T$4 -> 1.2272513e+08 | U15: =T15*U$4 -> 1.2550676e+08 | V15: =U15*V$4 -> 1.2834263e+08 | W15: =V15*W$4 -> 1.3123999e+08 | X15: =W15*X$4 -> 1.342017e+08 | Y15: =X15*Y$4 -> 1.3723011e+08 | ... AA15: =Z15*AA$4 -> 1.4349498e+08
A16: Iraq | B16: ='Country-Specific Data'!B11 -> 0 | C16: ='Country-Specific Data'!C11 -> 0 | D16: ='Country-Specific Data'!D11 -> 0 | E16: ='Country-Specific Data'!E11 -> 0 | F16: ='Country-Specific Data'!F11 -> 780000 | G16: ='Country-Specific Data'!G11 -> 0 | H16: ='Country-Specific Data'!H11 -> 0 | I16: ='Country-Specific Data'!I11 -> 0 | ... P16: ='Country-Specific Data'!P11 -> 0 | Q16: =AVERAGE(G16:P16)*Q$4 -> 0 | R16: =Q16*R$4 -> 0 | S16: =R16*S$4 -> 0 | T16: =S16*T$4 -> 0 | U16: =T16*U$4 -> 0 | V16: =U16*V$4 -> 0 | W16: =V16*W$4 -> 0 | X16: =W16*X$4 -> 0 | Y16: =X16*Y$4 -> 0 | ... AA16: =Z16*AA$4 -> 0
A17: Libya | B17: ='Country-Specific Data'!B12 -> 0 | C17: ='Country-Specific Data'!C12 -> 348539.99 | D17: ='Country-Specific Data'!D12 -> 18075419 | E17: ='Country-Specific Data'!E12 -> 0 | F17: ='Country-Specific Data'!F12 -> 0 | G17: ='Country-Specific Data'!G12 -> 0 | H17: ='Country-Specific Data'!H12 -> 0 | I17: ='Country-Specific Data'!I12 -> 0 | ... P17: ='Country-Specific Data'!P12 -> 0 | Q17: =AVERAGE(G17:P17)*Q$4 -> 638142.82 | R17: =Q17*R$4 -> 655013.37 | S17: =R17*S$4 -> 670662.25 | T17: =S17*T$4 -> 686093.99 | U17: =T17*U$4 -> 701644.68 | V17: =U17*V$4 -> 717498.58 | W17: =V17*W$4 -> 733696.25 | X17: =W17*X$4 -> 750253.68 | Y17: =X17*Y$4 -> 767183.98 | ... AA17: =Z17*AA$4 -> 802207.71
A18: Mali | B18: ='Country-Specific Data'!B13 -> 0 | C18: ='Country-Specific Data'!C13 -> 0 | D18: ='Country-Specific Data'!D13 -> 0 | E18: ='Country-Specific Data'!E13 -> 0 | F18: ='Country-Specific Data'!F13 -> 0 | G18: ='Country-Specific Data'!G13 -> 0 | H18: ='Country-Specific Data'!H13 -> 0 | I18: ='Country-Specific Data'!I13 -> 0 | ... P18: ='Country-Specific Data'!P13 -> 0 | Q18: =AVERAGE(G18:P18)*Q$4 -> 0 | R18: =Q18*R$4 -> 0 | S18: =R18*S$4 -> 0 | T18: =S18*T$4 -> 0 | U18: =T18*U$4 -> 0 | V18: =U18*V$4 -> 0 | W18: =V18*W$4 -> 0 | X18: =W18*X$4 -> 0 | Y18: =X18*Y$4 -> 0 | ... AA18: =Z18*AA$4 -> 0
A19: North Korea | B19: ='Country-Specific Data'!B14 -> 0 | C19: ='Country-Specific Data'!C14 -> 0 | D19: ='Country-Specific Data'!D14 -> 0 | E19: ='Country-Specific Data'!E14 -> 0 | F19: ='Country-Specific Data'!F14 -> 207805.23 | G19: ='Country-Specific Data'!G14 -> 0 | H19: ='Country-Specific Data'!H14 -> 0 | I19: ='Country-Specific Data'!I14 -> 0 | ... P19: ='Country-Specific Data'!P14 -> 860000 | Q19: =AVERAGE(G19:P19)*Q$4 -> 52842490 | R19: =Q19*R$4 -> 54239484 | S19: =R19*S$4 -> 55535315 | T19: =S19*T$4 -> 56813167 | U19: =T19*U$4 -> 58100868 | V19: =U19*V$4 -> 59413677 | W19: =V19*W$4 -> 60754953 | X19: =W19*X$4 -> 62126018 | Y19: =X19*Y$4 -> 63527960 | ... AA19: =Z19*AA$4 -> 66428159
... A24: Zimbabwe | B24: ='Country-Specific Data'!B19 -> 0 | C24: ='Country-Specific Data'!C19 -> 0 | D24: ='Country-Specific Data'!D19 -> 0 | E24: ='Country-Specific Data'!E19 -> 0 | F24: ='Country-Specific Data'!F19 -> 0 | G24: ='Country-Specific Data'!G19 -> 2485890 | H24: ='Country-Specific Data'!H19 -> 0 | I24: ='Country-Specific Data'!I19 -> 0 | ... P24: ='Country-Specific Data'!P19 -> 0 | Q24: =AVERAGE(G24:P24)*Q$4 -> 2139774.6 | R24: =Q24*R$4 -> 2196343.7 | S24: =R24*S$4 -> 2248816.4 | T24: =S24*T$4 -> 2300561 | U24: =T24*U$4 -> 2352704.5 | V24: =U24*V$4 -> 2405864.6 | W24: =V24*W$4 -> 2460177.5 | X24: =W24*X$4 -> 2515696.7 | Y24: =X24*Y$4 -> 2572466.1 | ... AA24: =Z24*AA$4 -> 2689905.2
A26: Program Projections
A27: EO 13382 | B27: ='Action-Based Data'!C4 -> 0 | C27: ='Action-Based Data'!D4 -> 0 | D27: ='Action-Based Data'!E4 -> 1782074.3 | E27: ='Action-Based Data'!F4 -> 9492525 | F27: ='Action-Based Data'!G4 -> 605950 | G27: ='Action-Based Data'!H4 -> 0 | H27: ='Action-Based Data'!I4 -> 0 | I27: ='Action-Based Data'!J4 -> 0 | ... P27: ='Action-Based Data'!Q4 -> 0 | Q27: =AVERAGE(G27:P27)*Q$4 -> 0 | R27: =Q27*R$4 -> 0 | S27: =R27*S$4 -> 0 | T27: =S27*T$4 -> 0 | U27: =T27*U$4 -> 0 | V27: =U27*V$4 -> 0 | W27: =V27*W$4 -> 0 | X27: =W27*X$4 -> 0 | Y27: =X27*Y$4 -> 0 | ... AA27: =Z27*AA$4 -> 0
A28: FNKSR | B28: ='Action-Based Data'!C5 -> 0 | C28: ='Action-Based Data'!D5 -> 0 | D28: ='Action-Based Data'!E5 -> 176879.49 | E28: ='Action-Based Data'!F5 -> 16418163 | F28: ='Action-Based Data'!G5 -> 58086.08 | G28: ='Action-Based Data'!H5 -> 0 | H28: ='Action-Based Data'!I5 -> 334800 | I28: ='Action-Based Data'!J5 -> 0 | ... P28: ='Action-Based Data'!Q5 -> 0 | Q28: =AVERAGE(G28:P28)*Q$4 -> 226153.9 | R28: =Q28*R$4 -> 232132.72 | S28: =R28*S$4 -> 237678.59 | T28: =S28*T$4 -> 243147.5 | U28: =T28*U$4 -> 248658.57 | V28: =U28*V$4 -> 254277.1 | W28: =V28*W$4 -> 260017.45 | X28: =W28*X$4 -> 265885.31 | Y28: =X28*Y$4 -> 271885.3 | ... AA28: =Z28*AA$4 -> 284297.49
A29: GMSR | B29: ='Action-Based Data'!C6 -> 0 | C29: ='Action-Based Data'!D6 -> 0 | D29: ='Action-Based Data'!E6 -> 0 | E29: ='Action-Based Data'!F6 -> 0 | F29: ='Action-Based Data'!G6 -> 0 | G29: ='Action-Based Data'!H6 -> 0 | H29: ='Action-Based Data'!I6 -> 0 | I29: ='Action-Based Data'!J6 -> 0 | ... P29: ='Action-Based Data'!Q6 -> 45179 | Q29: =AVERAGE(G29:P29)*Q$4 -> 4651.7078 | R29: =Q29*R$4 -> 4774.6847 | S29: =R29*S$4 -> 4888.7564 | T29: =S29*T$4 -> 5001.2453 | U29: =T29*U$4 -> 5114.6012 | V29: =U29*V$4 -> 5230.1673 | W29: =V29*W$4 -> 5348.2394 | X29: =W29*X$4 -> 5468.9339 | Y29: =X29*Y$4 -> 5592.3463 | ... AA29: =Z29*AA$4 -> 5847.65
A30: GTSR | B30: ='Action-Based Data'!C7 -> 0 | C30: ='Action-Based Data'!D7 -> 0 | D30: ='Action-Based Data'!E7 -> 0 | E30: ='Action-Based Data'!F7 -> 49827.28 | F30: ='Action-Based Data'!G7 -> 1730243.2 | G30: ='Action-Based Data'!H7 -> 0 | H30: ='Action-Based Data'!I7 -> 0 | I30: ='Action-Based Data'!J7 -> 0 | ... P30: ='Action-Based Data'!Q7 -> 0 | Q30: =AVERAGE(G30:P30)*Q$4 -> 949319.17 | R30: =Q30*R$4 -> 974416.27 | S30: =R30*S$4 -> 997695.98 | T30: =S30*T$4 -> 1020652.7 | U30: =T30*U$4 -> 1043786.3 | V30: =U30*V$4 -> 1067371 | W30: =V30*W$4 -> 1091467.1 | X30: =W30*X$4 -> 1116098.4 | Y30: =X30*Y$4 -> 1141284.4 | ... AA30: =Z30*AA$4 -> 1193386.7
A31: NTSR | B31: ='Action-Based Data'!C8 -> 0 | C31: ='Action-Based Data'!D8 -> 0 | D31: ='Action-Based Data'!E8 -> 0 | E31: ='Action-Based Data'!F8 -> 138798 | F31: ='Action-Based Data'!G8 -> 83657.6 | G31: ='Action-Based Data'!H8 -> 0 | H31: ='Action-Based Data'!I8 -> 0 | I31: ='Action-Based Data'!J8 -> 0 | ... P31: ='Action-Based Data'!Q8 -> 0 | Q31: =AVERAGE(G31:P31)*Q$4 -> 589.09174 | R31: =Q31*R$4 -> 604.66552 | S31: =R31*S$4 -> 619.11154 | T31: =S31*T$4 -> 633.35712 | U31: =T31*U$4 -> 647.7125 | V31: =U31*V$4 -> 662.34778 | W31: =V31*W$4 -> 677.30042 | X31: =W31*X$4 -> 692.58515 | Y31: =X31*Y$4 -> 708.21409 | ... AA31: =Z31*AA$4 -> 740.54571
A32: TCO | B32: ='Action-Based Data'!C9 -> 0 | C32: ='Action-Based Data'!D9 -> 0 | D32: ='Action-Based Data'!E9 -> 0 | E32: ='Action-Based Data'!F9 -> 0 | F32: ='Action-Based Data'!G9 -> 0 | G32: ='Action-Based Data'!H9 -> 0 | H32: ='Action-Based Data'!I9 -> 0 | I32: ='Action-Based Data'!J9 -> 0 | ... P32: ='Action-Based Data'!Q9 -> 0 | Q32: =AVERAGE(G32:P32)*Q$4 -> 0 | R32: =Q32*R$4 -> 0 | S32: =R32*S$4 -> 0 | T32: =S32*T$4 -> 0 | U32: =T32*U$4 -> 0 | V32: =U32*V$4 -> 0 | W32: =V32*W$4 -> 0 | X32: =W32*X$4 -> 0 | Y32: =X32*Y$4 -> 0 | ... AA32: =Z32*AA$4 -> 0
A33: WMDPSR | B33: ='Action-Based Data'!C10 -> 2270531.2 | C33: ='Action-Based Data'!D10 -> 201000 | D33: ='Action-Based Data'!E10 -> 20800 | E33: ='Action-Based Data'!F10 -> 200004.62 | F33: ='Action-Based Data'!G10 -> 52644897 | G33: ='Action-Based Data'!H10 -> 0 | H33: ='Action-Based Data'!I10 -> 39399.529 | I33: ='Action-Based Data'!J10 -> 0 | ... P33: ='Action-Based Data'!Q10 -> 0 | Q33: =AVERAGE(G33:P33)*Q$4 -> 31472629 | R33: =Q33*R$4 -> 32304669 | S33: =R33*S$4 -> 33076458 | T33: =S33*T$4 -> 33837537 | U33: =T33*U$4 -> 34604484 | V33: =U33*V$4 -> 35386383 | W33: =V33*W$4 -> 36185238 | X33: =W33*X$4 -> 37001835 | Y33: =X33*Y$4 -> 37836822 | ... AA33: =Z33*AA$4 -> 39564161
A35: Adjusted Russia Projections | B35: ='Adjusted Russia Projections'!B6 -> 0 | C35: ='Adjusted Russia Projections'!C6 -> 0 | D35: ='Adjusted Russia Projections'!D6 -> 0 | E35: ='Adjusted Russia Projections'!E6 -> 0 | F35: ='Adjusted Russia Projections'!F6 -> 0 | G35: ='Adjusted Russia Projections'!G6 -> 0 | H35: ='Adjusted Russia Projections'!H6 -> 0 | I35: ='Adjusted Russia Projections'!I6 -> 0 | ... AA35: ='Adjusted Russia Projections'!AA6 -> 5.1558953e+08
A37: Total | B37: =SUM(B8:B24,B27:B33,B35) -> 89753233 | C37: =SUM(C8:C24,C27:C33,C35) -> 625249095 | D37: =SUM(D8:D24,D27:D33,D35) -> 5.2583728e+08 | E37: =SUM(E8:E24,E27:E33,E35) -> 1.3276509e+09 | F37: =SUM(F8:F24,F27:F33,F35) -> 2.7203894e+08 | G37: =SUM(G8:G24,G27:G33,G35) -> 3.454362e+08 | H37: =SUM(H8:H24,H27:H33,H35) -> 1.2169374e+08 | I37: =SUM(I8:I24,I27:I33,I35) -> 3443035 | ... AA37: =SUM(AA8:AA24,AA27:AA33,AA35) -> 8.3779366e+08

Sheet Adjusted Russia Projections
A1: Fiscal Year | B1: 2011 | C1: 2012 | D1: 2013 | E1: 2014 | F1: 2015 | G1: 2016 | H1: 2017 | I1: 2018 | J1: 2019 | K1: 2020 | L1: 2021 | M1: 2022 | N1: 2023 | O1: 2024 | P1: 2025 | Q1: 2026 | R1: 2027 | S1: 2028 | T1: 2029 | U1: 2030 | V1: 2031 | W1: 2032 | X1: 2033 | Y1: 2034 | Z1: 2035 | AA1: 2036
A2: Winter 2026 Russia Actuals/Projections | B2: ='Fiscal Year Projections'!B20 -> 0 | C2: ='Fiscal Year Projections'!C20 -> 0 | D2: ='Fiscal Year Projections'!D20 -> 0 | E2: ='Fiscal Year Projections'!E20 -> 0 | F2: ='Fiscal Year Projections'!F20 -> 0 | G2: ='Fiscal Year Projections'!G20 -> 0 | H2: ='Fiscal Year Projections'!H20 -> 0 | I2: ='Fiscal Year Projections'!I20 -> 0 | ... AA2: ='Fiscal Year Projections'!AA20 -> 2731652.3
A4: Winter 2026 Iran Actuals/Projections | B4: ='Fiscal Year Projections'!B15 -> 729194.33 | C4: ='Fiscal Year Projections'!C15 -> 6150319 | D4: ='Fiscal Year Projections'!D15 -> 1.6640826e+08 | E4: ='Fiscal Year Projections'!E15 -> 3.2276752e+08 | F4: ='Fiscal Year Projections'!F15 -> 1.0897463e+08 | G4: ='Fiscal Year Projections'!G15 -> 9394493 | H4: ='Fiscal Year Projections'!H15 -> 1.2023835e+08 | I4: ='Fiscal Year Projections'!I15 -> 2720400 | ... AA4: ='Fiscal Year Projections'!AA15 -> 1.4349498e+08
A6: Winter 2026 Added Russia Projecton | B6: 0 | C6: 0 | D6: 0 | E6: 0 | F6: 0 | G6: 0 | H6: 0 | I6: 0 | J6: 0 | K6: 0 | L6: 0 | M6: 0 | N6: 0 | O6: 0 | P6: 0 | Q6: 0 | R6: 0 | S6: 0 | T6: =T2*$B$21*0.4 -> 4.409617e+08 | U6: =U2*$B$21*0.4 -> 4.5095634e+08 | V6: =V2*$B$21*0.4 -> 4.6114585e+08 | W6: =W2*$B$21*0.4 -> 4.7155631e+08 | X6: =X2*$B$21*0.4 -> 4.8219799e+08 | Y6: =Y2*$B$21*0.4 -> 4.9307931e+08 | Z6: =Z2*$B$21*0.4 -> 5.0420761e+08 | AA6: =AA2*$B$21*0.4 -> 5.1558953e+08
A9: Estimate Basis
A11: 2022 Russia GDP (USD) | B11: 2240000000000
A12: 2022 Iran GDP (USD) | B12: 346480000000
A13: GDP Ratio | B13: =B11/B12 -> 6.4650196
A14: Source: IMF World Economic Outlook (https://www.imf.org/external/datamapper/datasets/WEO)
A16: Average Collection, Prior Russia Sanctions | B16: =AVERAGE(E2:P2) -> 1758731
A17: Average Collections, Iran Sanctions | B17: =AVERAGE(E4:P4) -> 1.2836548e+08
A19: Russia Collections to Russia GDP Ratio | B19: =B16/B11 -> 7.8514778e-07
A20: Iran Collections to Iran GDP Ratio | B20: =B17/B12 -> 0.00037048453
A21: Anticipated Increase in Russia Collections | B21: =B20/B19 -> 471.86599
A23: *Anticipated first year of full revenue is 2029, because current Russian sanctions penalties are collected an average of 8 years after the start of the violation
A24: ** Assuming a 40% increase in compliance vs Iran given existing shifts to decouple from Russia

Sheet Country-Specific Data
A1: Country (FY) | B1: 2011 | C1: 2012 | D1: 2013 | E1: 2014 | F1: 2015 | G1: 2016 | H1: 2017 | I1: 2018 | J1: 2019 | K1: 2020 | L1: 2021 | M1: 2022 | N1: 2023 | O1: 2024 | P1: 2025
A3: Afghanistan | B3: =SUMIFS(ALLData!$M$2:$M$400, ALLData!$B$2:$B$400, 'Country-Specific Data'!B$1, ALLData!$G$2:$G$400, 'Country-Specific Data'!$A3) -> 0 | C3: =SUMIFS(ALLData!$M$2:$M$400, ALLData!$B$2:$B$400, 'Country-Specific Data'!C$1, ALLData!$G$2:$G$400, 'Country-Specific Data'!$A3) -> 0 | D3: =SUMIFS(ALLData!$M$2:$M$400, ALLData!$B$2:$B$400, 'Country-Specific Data'!D$1, ALLData!$G$2:$G$400, 'Country-Specific Data'!$A3) -> 0 | E3: =SUMIFS(ALLData!$M$2:$M$400, ALLData!$B$2:$B$400, 'Country-Specific Data'!E$1, ALLData!$G$2:$G$400, 'Country-Specific Data'!$A3) -> 0 | F3: =SUMIFS(ALLData!$M$2:$M$400, ALLData!$B$2:$B$400, 'Country-Specific Data'!F$1, ALLData!$G$2:$G$400, 'Country-Specific Data'!$A3) -> 0 | G3: =SUMIFS(ALLData!$M$2:$M$400, ALLData!$B$2:$B$400, 'Country-Specific Data'!G$1, ALLData!$G$2:$G$400, 'Country-Specific Data'!$A3) -> 0 | H3: =SUMIFS(ALLData!$M$2:$M$400, ALLData!$B$2:$B$400, 'Country-Specific Data'!H$1, ALLData!$G$2:$G$400, 'Country-Specific Data'!$A3) -> 0 | I3: =SUMIFS(ALLData!$M$2:$M$400, ALLData!$B$2:$B$400, 'Country-Specific Data'!I$1, ALLData!$G$2:$G$400, 'Country-Specific Data'!$A3) -> 0 | ... P3: =SUMIFS(ALLData!$M$2:$M$400, ALLData!$B$2:$B$400, 'Country-Specific Data'!P$1, ALLData!$G$2:$G$400, 'Country-Specific Data'!$A3) -> 0
A4: Belarus | B4: =SUMIFS(ALLData!$M$2:$M$400, ALLData!$B$2:$B$400, 'Country-Specific Data'!B$1, ALLData!$G$2:$G$400, 'Country-Specific Data'!$A4) -> 0 | C4: =SUMIFS(ALLData!$M$2:$M$400, ALLData!$B$2:$B$400, 'Country-Specific Data'!C$1, ALLData!$G$2:$G$400, 'Country-Specific Data'!$A4) -> 0 | D4: =SUMIFS(ALLData!$M$2:$M$400, ALLData!$B$2:$B$400, 'Country-Specific Data'!D$1, ALLData!$G$2:$G$400, 'Country-Specific Data'!$A4) -> 0 | E4: =SUMIFS(ALLData!$M$2:$M$400, ALLData!$B$2:$B$400, 'Country-Specific Data'!E$1, ALLData!$G$2:$G$400, 'Country-Specific Data'!$A4) -> 0 | F4: =SUMIFS(ALLData!$M$2:$M$400, ALLData!$B$2:$B$400, 'Country-Specific Data'!F$1, ALLData!$G$2:$G$400, 'Country-Specific Data'!$A4) -> 0 | G4: =SUMIFS(ALLData!$M$2:$M$400, ALLData!$B$2:$B$400, 'Country-Specific Data'!G$1, ALLData!$G$2:$G$400, 'Country-Specific Data'!$A4) -> 0 | H4: =SUMIFS(ALLData!$M$2:$M$400, ALLData!$B$2:$B$400, 'Country-Specific Data'!H$1, ALLData!$G$2:$G$400, 'Country-Specific Data'!$A4) -> 0 | I4: =SUMIFS(ALLData!$M$2:$M$400, ALLData!$B$2:$B$400, 'Country-Specific Data'!I$1, ALLData!$G$2:$G$400, 'Country-Specific Data'!$A4) -> 0 | ... P4: =SUMIFS(ALLData!$M$2:$M$400, ALLData!$B$2:$B$400, 'Country-Specific Data'!P$1, ALLData!$G$2:$G$400, 'Country-Specific Data'!$A4) -> 0
A5: Burma | B5: =SUMIFS(ALLData!$M$2:$M$400, ALLData!$B$2:$B$400, 'Country-Specific Data'!B$1, ALLData!$G$2:$G$400, 'Country-Specific Data'!$A5) -> 0 | C5: =SUMIFS(ALLData!$M$2:$M$400, ALLData!$B$2:$B$400, 'Country-Specific Data'!C$1, ALLData!$G$2:$G$400, 'Country-Specific Data'!$A5) -> 18514021 | D5: =SUMIFS(ALLData!$M$2:$M$400, ALLData!$B$2:$B$400, 'Country-Specific Data'!D$1, ALLData!$G$2:$G$400, 'Country-Specific Data'!$A5) -> 1.3671728e+08 | E5: =SUMIFS(ALLData!$M$2:$M$400, ALLData!$B$2:$B$400, 'Country-Specific Data'!E$1, ALLData!$G$2:$G$400, 'Country-Specific Data'!$A5) -> 3082289.4 | F5: =SUMIFS(ALLData!$M$2:$M$400, ALLData!$B$2:$B$400, 'Country-Specific Data'!F$1, ALLData!$G$2:$G$400, 'Country-Specific Data'!$A5) -> 8925835.9 | G5: =SUMIFS(ALLData!$M$2:$M$400, ALLData!$B$2:$B$400, 'Country-Specific Data'!G$1, ALLData!$G$2:$G$400, 'Country-Specific Data'!$A5) -> 5231994.3 | H5: =SUMIFS(ALLData!$M$2:$M$400, ALLData!$B$2:$B$400, 'Country-Specific Data'!H$1, ALLData!$G$2:$G$400, 'Country-Specific Data'!$A5) -> 0 | I5: =SUMIFS(ALLData!$M$2:$M$400, ALLData!$B$2:$B$400, 'Country-Specific Data'!I$1, ALLData!$G$2:$G$400, 'Country-Specific Data'!$A5) -> 0 | ... P5: =SUMIFS(ALLData!$M$2:$M$400, ALLData!$B$2:$B$400, 'Country-Specific Data'!P$1, ALLData!$G$2:$G$400, 'Country-Specific Data'!$A5) -> 0
A6: Central African Republic | B6: =SUMIFS(ALLData!$M$2:$M$400, ALLData!$B$2:$B$400, 'Country-Specific Data'!B$1, ALLData!$G$2:$G$400, 'Country-Specific Data'!$A6) -> 0 | C6: =SUMIFS(ALLData!$M$2:$M$400, ALLData!$B$2:$B$400, 'Country-Specific Data'!C$1, ALLData!$G$2:$G$400, 'Country-Specific Data'!$A6) -> 0 | D6: =SUMIFS(ALLData!$M$2:$M$400, ALLData!$B$2:$B$400, 'Country-Specific Data'!D$1, ALLData!$G$2:$G$400, 'Country-Specific Data'!$A6) -> 0 | E6: =SUMIFS(ALLData!$M$2:$M$400, ALLData!$B$2:$B$400, 'Country-Specific Data'!E$1, ALLData!$G$2:$G$400, 'Country-Specific Data'!$A6) -> 0 | F6: =SUMIFS(ALLData!$M$2:$M$400, ALLData!$B$2:$B$400, 'Country-Specific Data'!F$1, ALLData!$G$2:$G$400, 'Country-Specific Data'!$A6) -> 0 | G6: =SUMIFS(ALLData!$M$2:$M$400, ALLData!$B$2:$B$400, 'Country-Specific Data'!G$1, ALLData!$G$2:$G$400, 'Country-Specific Data'!$A6) -> 0 | H6: =SUMIFS(ALLData!$M$2:$M$400, ALLData!$B$2:$B$400, 'Country-Specific Data'!H$1, ALLData!$G$2:$G$400, 'Country-Specific Data'!$A6) -> 0 | I6: =SUMIFS(ALLData!$M$2:$M$400, ALLData!$B$2:$B$400, 'Country-Specific Data'!I$1, ALLData!$G$2:$G$400, 'Country-Specific Data'!$A6) -> 0 | ... P6: =SUMIFS(ALLData!$M$2:$M$400, ALLData!$B$2:$B$400, 'Country-Specific Data'!P$1, ALLData!$G$2:$G$400, 'Country-Specific Data'!$A6) -> 0
A7: Cuba | B7: =SUMIFS(ALLData!$M$2:$M$400, ALLData!$B$2:$B$400, 'Country-Specific Data'!B$1, ALLData!$G$2:$G$400, 'Country-Specific Data'!$A7) -> 86344238 | C7: =SUMIFS(ALLData!$M$2:$M$400, ALLData!$B$2:$B$400, 'Country-Specific Data'!C$1, ALLData!$G$2:$G$400, 'Country-Specific Data'!$A7) -> 5.9306532e+08 | D7: =SUMIFS(ALLData!$M$2:$M$400, ALLData!$B$2:$B$400, 'Country-Specific Data'!D$1, ALLData!$G$2:$G$400, 'Country-Specific Data'!$A7) -> 8508305.9 | E7: =SUMIFS(ALLData!$M$2:$M$400, ALLData!$B$2:$B$400, 'Country-Specific Data'!E$1, ALLData!$G$2:$G$400, 'Country-Specific Data'!$A7) -> 80845798 | F7: =SUMIFS(ALLData!$M$2:$M$400, ALLData!$B$2:$B$400, 'Country-Specific Data'!F$1, ALLData!$G$2:$G$400, 'Country-Specific Data'!$A7) -> 3714101.4 | G7: =SUMIFS(ALLData!$M$2:$M$400, ALLData!$B$2:$B$400, 'Country-Specific Data'!G$1, ALLData!$G$2:$G$400, 'Country-Specific Data'!$A7) -> 3633356 | H7: =SUMIFS(ALLData!$M$2:$M$400, ALLData!$B$2:$B$400, 'Country-Specific Data'!H$1, ALLData!$G$2:$G$400, 'Country-Specific Data'!$A7) -> 1069620.1 | I7: =SUMIFS(ALLData!$M$2:$M$400, ALLData!$B$2:$B$400, 'Country-Specific Data'!I$1, ALLData!$G$2:$G$400, 'Country-Specific Data'!$A7) -> 204277 | ... P7: =SUMIFS(ALLData!$M$2:$M$400, ALLData!$B$2:$B$400, 'Country-Specific Data'!P$1, ALLData!$G$2:$G$400, 'Country-Specific Data'!$A7) -> 925170
A8: Democratic Republic of the Congo | B8: =SUMIFS(ALLData!$M$2:$M$400, ALLData!$B$2:$B$400, 'Country-Specific Data'!B$1, ALLData!$G$2:$G$400, 'Country-Specific Data'!$A8) -> 0 | C8: =SUMIFS(ALLData!$M$2:$M$400, ALLData!$B$2:$B$400, 'Country-Specific Data'!C$1, ALLData!$G$2:$G$400, 'Country-Specific Data'!$A8) -> 0 | D8: =SUMIFS(ALLData!$M$2:$M$400, ALLData!$B$2:$B$400, 'Country-Specific Data'!D$1, ALLData!$G$2:$G$400, 'Country-Specific Data'!$A8) -> 0 | E8: =SUMIFS(ALLData!$M$2:$M$400, ALLData!$B$2:$B$400, 'Country-Specific Data'!E$1, ALLData!$G$2:$G$400, 'Country-Specific Data'!$A8) -> 0 | F8: =SUMIFS(ALLData!$M$2:$M$400, ALLData!$B$2:$B$400, 'Country-Specific Data'!F$1, ALLData!$G$2:$G$400, 'Country-Specific Data'!$A8) -> 0 | G8: =SUMIFS(ALLData!$M$2:$M$400, ALLData!$B$2:$B$400, 'Country-Specific Data'!G$1, ALLData!$G$2:$G$400, 'Country-Specific Data'!$A8) -> 0 | H8: =SUMIFS(ALLData!$M$2:$M$400, ALLData!$B$2:$B$400, 'Country-Specific Data'!H$1, ALLData!$G$2:$G$400, 'Country-Specific Data'!$A8) -> 0 | I8: =SUMIFS(ALLData!$M$2:$M$400, ALLData!$B$2:$B$400, 'Country-Specific Data'!I$1, ALLData!$G$2:$G$400, 'Country-Specific Data'!$A8) -> 0 | ... P8: =SUMIFS(ALLData!$M$2:$M$400, ALLData!$B$2:$B$400, 'Country-Specific Data'!P$1, ALLData!$G$2:$G$400, 'Country-Specific Data'!$A8) -> 0
A9: Ethopia | B9: =SUMIFS(ALLData!$M$2:$M$400, ALLData!$B$2:$B$400, 'Country-Specific Data'!B$1, ALLData!$G$2:$G$400, 'Country-Specific Data'!$A9) -> 0 | C9: =SUMIFS(ALLData!$M$2:$M$400, ALLData!$B$2:$B$400, 'Country-Specific Data'!C$1, ALLData!$G$2:$G$400, 'Country-Specific Data'!$A9) -> 0 | D9: =SUMIFS(ALLData!$M$2:$M$400, ALLData!$B$2:$B$400, 'Country-Specific Data'!D$1, ALLData!$G$2:$G$400, 'Country-Specific Data'!$A9) -> 0 | E9: =SUMIFS(ALLData!$M$2:$M$400, ALLData!$B$2:$B$400, 'Country-Specific Data'!E$1, ALLData!$G$2:$G$400, 'Country-Specific Data'!$A9) -> 0 | F9: =SUMIFS(ALLData!$M$2:$M$400, ALLData!$B$2:$B$400, 'Country-Specific Data'!F$1, ALLData!$G$2:$G$400, 'Country-Specific Data'!$A9) -> 0 | G9: =SUMIFS(ALLData!$M$2:$M$400, ALLData!$B$2:$B$400, 'Country-Specific Data'!G$1, ALLData!$G$2:$G$400, 'Country-Specific Data'!$A9) -> 0 | H9: =SUMIFS(ALLData!$M$2:$M$400, ALLData!$B$2:$B$400, 'Country-Specific Data'!H$1, ALLData!$G$2:$G$400, 'Country-Specific Data'!$A9) -> 0 | I9: =SUMIFS(ALLData!$M$2:$M$400, ALLData!$B$2:$B$400, 'Country-Specific Data'!I$1, ALLData!$G$2:$G$400, 'Country-Specific Data'!$A9) -> 0 | ... P9: =SUMIFS(ALLData!$M$2:$M$400, ALLData!$B$2:$B$400, 'Country-Specific Data'!P$1, ALLData!$G$2:$G$400, 'Country-Specific Data'!$A9) -> 0
A10: Iran | B10: =SUMIFS(ALLData!$M$2:$M$400, ALLData!$B$2:$B$400, 'Country-Specific Data'!B$1, ALLData!$G$2:$G$400, 'Country-Specific Data'!$A10) -> 729194.33 | C10: =SUMIFS(ALLData!$M$2:$M$400, ALLData!$B$2:$B$400, 'Country-Specific Data'!C$1, ALLData!$G$2:$G$400, 'Country-Specific Data'!$A10) -> 6150319 | D10: =SUMIFS(ALLData!$M$2:$M$400, ALLData!$B$2:$B$400, 'Country-Specific Data'!D$1, ALLData!$G$2:$G$400, 'Country-Specific Data'!$A10) -> 1.6640826e+08 | E10: =SUMIFS(ALLData!$M$2:$M$400, ALLData!$B$2:$B$400, 'Country-Specific Data'!E$1, ALLData!$G$2:$G$400, 'Country-Specific Data'!$A10) -> 3.2276752e+08 | F10: =SUMIFS(ALLData!$M$2:$M$400, ALLData!$B$2:$B$400, 'Country-Specific Data'!F$1, ALLData!$G$2:$G$400, 'Country-Specific Data'!$A10) -> 1.0897463e+08 | G10: =SUMIFS(ALLData!$M$2:$M$400, ALLData!$B$2:$B$400, 'Country-Specific Data'!G$1, ALLData!$G$2:$G$400, 'Country-Specific Data'!$A10) -> 9394493 | H10: =SUMIFS(ALLData!$M$2:$M$400, ALLData!$B$2:$B$400, 'Country-Specific Data'!H$1, ALLData!$G$2:$G$400, 'Country-Specific Data'!$A10) -> 1.2023835e+08 | I10: =SUMIFS(ALLData!$M$2:$M$400, ALLData!$B$2:$B$400, 'Country-Specific Data'!I$1, ALLData!$G$2:$G$400, 'Country-Specific Data'!$A10) -> 2720400 | ... P10: =SUMIFS(ALLData!$M$2:$M$400, ALLData!$B$2:$B$400, 'Country-Specific Data'!P$1, ALLData!$G$2:$G$400, 'Country-Specific Data'!$A10) -> 17833143
A11: Iraq | B11: =SUMIFS(ALLData!$M$2:$M$400, ALLData!$B$2:$B$400, 'Country-Specific Data'!B$1, ALLData!$G$2:$G$400, 'Country-Specific Data'!$A11) -> 0 | C11: =SUMIFS(ALLData!$M$2:$M$400, ALLData!$B$2:$B$400, 'Country-Specific Data'!C$1, ALLData!$G$2:$G$400, 'Country-Specific Data'!$A11) -> 0 | D11: =SUMIFS(ALLData!$M$2:$M$400, ALLData!$B$2:$B$400, 'Country-Specific Data'!D$1, ALLData!$G$2:$G$400, 'Country-Specific Data'!$A11) -> 0 | E11: =SUMIFS(ALLData!$M$2:$M$400, ALLData!$B$2:$B$400, 'Country-Specific Data'!E$1, ALLData!$G$2:$G$400, 'Country-Specific Data'!$A11) -> 0 | F11: =SUMIFS(ALLData!$M$2:$M$400, ALLData!$B$2:$B$400, 'Country-Specific Data'!F$1, ALLData!$G$2:$G$400, 'Country-Specific Data'!$A11) -> 780000 | G11: =SUMIFS(ALLData!$M$2:$M$400, ALLData!$B$2:$B$400, 'Country-Specific Data'!G$1, ALLData!$G$2:$G$400, 'Country-Specific Data'!$A11) -> 0 | H11: =SUMIFS(ALLData!$M$2:$M$400, ALLData!$B$2:$B$400, 'Country-Specific Data'!H$1, ALLData!$G$2:$G$400, 'Country-Specific Data'!$A11) -> 0 | I11: =SUMIFS(ALLData!$M$2:$M$400, ALLData!$B$2:$B$400, 'Country-Specific Data'!I$1, ALLData!$G$2:$G$400, 'Country-Specific Data'!$A11) -> 0 | ... P11: =SUMIFS(ALLData!$M$2:$M$400, ALLData!$B$2:$B$400, 'Country-Specific Data'!P$1, ALLData!$G$2:$G$400, 'Country-Specific Data'!$A11) -> 0
A12: Libya | B12: =SUMIFS(ALLData!$M$2:$M$400, ALLData!$B$2:$B$400, 'Country-Specific Data'!B$1, ALLData!$G$2:$G$400, 'Country-Specific Data'!$A12) -> 0 | C12: =SUMIFS(ALLData!$M$2:$M$400, ALLData!$B$2:$B$400, 'Country-Specific Data'!C$1, ALLData!$G$2:$G$400, 'Country-Specific Data'!$A12) -> 348539.99 | D12: =SUMIFS(ALLData!$M$2:$M$400, ALLData!$B$2:$B$400, 'Country-Specific Data'!D$1, ALLData!$G$2:$G$400, 'Country-Specific Data'!$A12) -> 18075419 | E12: =SUMIFS(ALLData!$M$2:$M$400, ALLData!$B$2:$B$400, 'Country-Specific Data'!E$1, ALLData!$G$2:$G$400, 'Country-Specific Data'!$A12) -> 0 | F12: =SUMIFS(ALLData!$M$2:$M$400, ALLData!$B$2:$B$400, 'Country-Specific Data'!F$1, ALLData!$G$2:$G$400, 'Country-Specific Data'!$A12) -> 0 | G12: =SUMIFS(ALLData!$M$2:$M$400, ALLData!$B$2:$B$400, 'Country-Specific Data'!G$1, ALLData!$G$2:$G$400, 'Country-Specific Data'!$A12) -> 0 | H12: =SUMIFS(ALLData!$M$2:$M$400, ALLData!$B$2:$B$400, 'Country-Specific Data'!H$1, ALLData!$G$2:$G$400, 'Country-Specific Data'!$A12) -> 0 | I12: =SUMIFS(ALLData!$M$2:$M$400, ALLData!$B$2:$B$400, 'Country-Specific Data'!I$1, ALLData!$G$2:$G$400, 'Country-Specific Data'!$A12) -> 0 | ... P12: =SUMIFS(ALLData!$M$2:$M$400, ALLData!$B$2:$B$400, 'Country-Specific Data'!P$1, ALLData!$G$2:$G$400, 'Country-Specific Data'!$A12) -> 0
A13: Mali | B13: =SUMIFS(ALLData!$M$2:$M$400, ALLData!$B$2:$B$400, 'Country-Specific Data'!B$1, ALLData!$G$2:$G$400, 'Country-Specific Data'!$A13) -> 0 | C13: =SUMIFS(ALLData!$M$2:$M$400, ALLData!$B$2:$B$400, 'Country-Specific Data'!C$1, ALLData!$G$2:$G$400, 'Country-Specific Data'!$A13) -> 0 | D13: =SUMIFS(ALLData!$M$2:$M$400, ALLData!$B$2:$B$400, 'Country-Specific Data'!D$1, ALLData!$G$2:$G$400, 'Country-Specific Data'!$A13) -> 0 | E13: =SUMIFS(ALLData!$M$2:$M$400, ALLData!$B$2:$B$400, 'Country-Specific Data'!E$1, ALLData!$G$2:$G$400, 'Country-Specific Data'!$A13) -> 0 | F13: =SUMIFS(ALLData!$M$2:$M$400, ALLData!$B$2:$B$400, 'Country-Specific Data'!F$1, ALLData!$G$2:$G$400, 'Country-Specific Data'!$A13) -> 0 | G13: =SUMIFS(ALLData!$M$2:$M$400, ALLData!$B$2:$B$400, 'Country-Specific Data'!G$1, ALLData!$G$2:$G$400, 'Country-Specific Data'!$A13) -> 0 | H13: =SUMIFS(ALLData!$M$2:$M$400, ALLData!$B$2:$B$400, 'Country-Specific Data'!H$1, ALLData!$G$2:$G$400, 'Country-Specific Data'!$A13) -> 0 | I13: =SUMIFS(ALLData!$M$2:$M$400, ALLData!$B$2:$B$400, 'Country-Specific Data'!I$1, ALLData!$G$2:$G$400, 'Country-Specific Data'!$A13) -> 0 | ... P13: =SUMIFS(ALLData!$M$2:$M$400, ALLData!$B$2:$B$400, 'Country-Specific Data'!P$1, ALLData!$G$2:$G$400, 'Country-Specific Data'!$A13) -> 0
A14: North Korea | B14: =SUMIFS(ALLData!$M$2:$M$400, ALLData!$B$2:$B$400, 'Country-Specific Data'!B$1, ALLData!$G$2:$G$400, 'Country-Specific Data'!$A14) -> 0 | C14: =SUMIFS(ALLData!$M$2:$M$400, ALLData!$B$2:$B$400, 'Country-Specific Data'!C$1, ALLData!$G$2:$G$400, 'Country-Specific Data'!$A14) -> 0 | D14: =SUMIFS(ALLData!$M$2:$M$400, ALLData!$B$2:$B$400, 'Country-Specific Data'!D$1, ALLData!$G$2:$G$400, 'Country-Specific Data'!$A14) -> 0 | E14: =SUMIFS(ALLData!$M$2:$M$400, ALLData!$B$2:$B$400, 'Country-Specific Data'!E$1, ALLData!$G$2:$G$400, 'Country-Specific Data'!$A14) -> 0 | F14: =SUMIFS(ALLData!$M$2:$M$400, ALLData!$B$2:$B$400, 'Country-Specific Data'!F$1, ALLData!$G$2:$G$400, 'Country-Specific Data'!$A14) -> 207805.23 | G14: =SUMIFS(ALLData!$M$2:$M$400, ALLData!$B$2:$B$400, 'Country-Specific Data'!G$1, ALLData!$G$2:$G$400, 'Country-Specific Data'!$A14) -> 0 | H14: =SUMIFS(ALLData!$M$2:$M$400, ALLData!$B$2:$B$400, 'Country-Specific Data'!H$1, ALLData!$G$2:$G$400, 'Country-Specific Data'!$A14) -> 0 | I14: =SUMIFS(ALLData!$M$2:$M$400, ALLData!$B$2:$B$400, 'Country-Specific Data'!I$1, ALLData!$G$2:$G$400, 'Country-Specific Data'!$A14) -> 0 | ... P14: =SUMIFS(ALLData!$M$2:$M$400, ALLData!$B$2:$B$400, 'Country-Specific Data'!P$1, ALLData!$G$2:$G$400, 'Country-Specific Data'!$A14) -> 860000
... A19: Zimbabwe | B19: =SUMIFS(ALLData!$M$2:$M$400, ALLData!$B$2:$B$400, 'Country-Specific Data'!B$1, ALLData!$G$2:$G$400, 'Country-Specific Data'!$A19) -> 0 | C19: =SUMIFS(ALLData!$M$2:$M$400, ALLData!$B$2:$B$400, 'Country-Specific Data'!C$1, ALLData!$G$2:$G$400, 'Country-Specific Data'!$A19) -> 0 | D19: =SUMIFS(ALLData!$M$2:$M$400, ALLData!$B$2:$B$400, 'Country-Specific Data'!D$1, ALLData!$G$2:$G$400, 'Country-Specific Data'!$A19) -> 0 | E19: =SUMIFS(ALLData!$M$2:$M$400, ALLData!$B$2:$B$400, 'Country-Specific Data'!E$1, ALLData!$G$2:$G$400, 'Country-Specific Data'!$A19) -> 0 | F19: =SUMIFS(ALLData!$M$2:$M$400, ALLData!$B$2:$B$400, 'Country-Specific Data'!F$1, ALLData!$G$2:$G$400, 'Country-Specific Data'!$A19) -> 0 | G19: =SUMIFS(ALLData!$M$2:$M$400, ALLData!$B$2:$B$400, 'Country-Specific Data'!G$1, ALLData!$G$2:$G$400, 'Country-Specific Data'!$A19) -> 2485890 | H19: =SUMIFS(ALLData!$M$2:$M$400, ALLData!$B$2:$B$400, 'Country-Specific Data'!H$1, ALLData!$G$2:$G$400, 'Country-Specific Data'!$A19) -> 0 | I19: =SUMIFS(ALLData!$M$2:$M$400, ALLData!$B$2:$B$400, 'Country-Specific Data'!I$1, ALLData!$G$2:$G$400, 'Country-Specific Data'!$A19) -> 0 | ... P19: =SUMIFS(ALLData!$M$2:$M$400, ALLData!$B$2:$B$400, 'Country-Specific Data'!P$1, ALLData!$G$2:$G$400, 'Country-Specific Data'!$A19) -> 0
A21: Total | B21: =SUM(B3:B19) -> 87482702 | C21: =SUM(C3:C19) -> 625048095 | D21: =SUM(D3:D19) -> 5.2385753e+08 | E21: =SUM(E3:E19) -> 1.3013516e+09 | F21: =SUM(F3:F19) -> 2.1691611e+08 | G21: =SUM(G3:G19) -> 3.454362e+08 | H21: =SUM(H3:H19) -> 1.2131954e+08 | I21: =SUM(I3:I19) -> 3443035 | ... P21: =SUM(P3:P19) -> 22574771

Sheet Action-Based Data
A1: Fiscal Year | C1: 2011 | D1: 2012 | E1: 2013 | F1: 2014 | G1: 2015 | H1: 2016 | I1: 2017 | J1: 2018 | K1: 2019 | L1: 2020 | M1: 2021 | N1: 2022 | O1: 2023 | P1: 2024 | Q1: 2025
A3: Abreviation | B3: Full Program Title
A4: EO 13382 | B4: EO 13382 | C4: =SUMIFS(ALLData!$M$2:$M$400, ALLData!$B$2:$B$400, 'Action-Based Data'!C$1, ALLData!$G$2:$G$400, 'Action-Based Data'!$A4) -> 0 | D4: =SUMIFS(ALLData!$M$2:$M$400, ALLData!$B$2:$B$400, 'Action-Based Data'!D$1, ALLData!$G$2:$G$400, 'Action-Based Data'!$A4) -> 0 | E4: =SUMIFS(ALLData!$M$2:$M$400, ALLData!$B$2:$B$400, 'Action-Based Data'!E$1, ALLData!$G$2:$G$400, 'Action-Based Data'!$A4) -> 1782074.3 | F4: =SUMIFS(ALLData!$M$2:$M$400, ALLData!$B$2:$B$400, 'Action-Based Data'!F$1, ALLData!$G$2:$G$400, 'Action-Based Data'!$A4) -> 9492525 | G4: =SUMIFS(ALLData!$M$2:$M$400, ALLData!$B$2:$B$400, 'Action-Based Data'!G$1, ALLData!$G$2:$G$400, 'Action-Based Data'!$A4) -> 605950 | H4: =SUMIFS(ALLData!$M$2:$M$400, ALLData!$B$2:$B$400, 'Action-Based Data'!H$1, ALLData!$G$2:$G$400, 'Action-Based Data'!$A4) -> 0 | I4: =SUMIFS(ALLData!$M$2:$M$400, ALLData!$B$2:$B$400, 'Action-Based Data'!I$1, ALLData!$G$2:$G$400, 'Action-Based Data'!$A4) -> 0 | J4: =SUMIFS(ALLData!$M$2:$M$400, ALLData!$B$2:$B$400, 'Action-Based Data'!J$1, ALLData!$G$2:$G$400, 'Action-Based Data'!$A4) -> 0 | ... Q4: =SUMIFS(ALLData!$M$2:$M$400, ALLData!$B$2:$B$400, 'Action-Based Data'!Q$1, ALLData!$G$2:$G$400, 'Action-Based Data'!$A4) -> 0
A5: FNKSR | B5: Foreign Narcotics Trafficking Sanctions | C5: =SUMIFS(ALLData!$M$2:$M$400, ALLData!$B$2:$B$400, 'Action-Based Data'!C$1, ALLData!$G$2:$G$400, 'Action-Based Data'!$A5) -> 0 | D5: =SUMIFS(ALLData!$M$2:$M$400, ALLData!$B$2:$B$400, 'Action-Based Data'!D$1, ALLData!$G$2:$G$400, 'Action-Based Data'!$A5) -> 0 | E5: =SUMIFS(ALLData!$M$2:$M$400, ALLData!$B$2:$B$400, 'Action-Based Data'!E$1, ALLData!$G$2:$G$400, 'Action-Based Data'!$A5) -> 176879.49 | F5: =SUMIFS(ALLData!$M$2:$M$400, ALLData!$B$2:$B$400, 'Action-Based Data'!F$1, ALLData!$G$2:$G$400, 'Action-Based Data'!$A5) -> 16418163 | G5: =SUMIFS(ALLData!$M$2:$M$400, ALLData!$B$2:$B$400, 'Action-Based Data'!G$1, ALLData!$G$2:$G$400, 'Action-Based Data'!$A5) -> 58086.08 | H5: =SUMIFS(ALLData!$M$2:$M$400, ALLData!$B$2:$B$400, 'Action-Based Data'!H$1, ALLData!$G$2:$G$400, 'Action-Based Data'!$A5) -> 0 | I5: =SUMIFS(ALLData!$M$2:$M$400, ALLData!$B$2:$B$400, 'Action-Based Data'!I$1, ALLData!$G$2:$G$400, 'Action-Based Data'!$A5) -> 334800 | J5: =SUMIFS(ALLData!$M$2:$M$400, ALLData!$B$2:$B$400, 'Action-Based Data'!J$1, ALLData!$G$2:$G$400, 'Action-Based Data'!$A5) -> 0 | ... Q5: =SUMIFS(ALLData!$M$2:$M$400, ALLData!$B$2:$B$400, 'Action-Based Data'!Q$1, ALLData!$G$2:$G$400, 'Action-Based Data'!$A5) -> 0
A6: GMSR | B6: Global Magnitsky Sanctions | C6: =SUMIFS(ALLData!$M$2:$M$400, ALLData!$B$2:$B$400, 'Action-Based Data'!C$1, ALLData!$G$2:$G$400, 'Action-Based Data'!$A6) -> 0 | D6: =SUMIFS(ALLData!$M$2:$M$400, ALLData!$B$2:$B$400, 'Action-Based Data'!D$1, ALLData!$G$2:$G$400, 'Action-Based Data'!$A6) -> 0 | E6: =SUMIFS(ALLData!$M$2:$M$400, ALLData!$B$2:$B$400, 'Action-Based Data'!E$1, ALLData!$G$2:$G$400, 'Action-Based Data'!$A6) -> 0 | F6: =SUMIFS(ALLData!$M$2:$M$400, ALLData!$B$2:$B$400, 'Action-Based Data'!F$1, ALLData!$G$2:$G$400, 'Action-Based Data'!$A6) -> 0 | G6: =SUMIFS(ALLData!$M$2:$M$400, ALLData!$B$2:$B$400, 'Action-Based Data'!G$1, ALLData!$G$2:$G$400, 'Action-Based Data'!$A6) -> 0 | H6: =SUMIFS(ALLData!$M$2:$M$400, ALLData!$B$2:$B$400, 'Action-Based Data'!H$1, ALLData!$G$2:$G$400, 'Action-Based Data'!$A6) -> 0 | I6: =SUMIFS(ALLData!$M$2:$M$400, ALLData!$B$2:$B$400, 'Action-Based Data'!I$1, ALLData!$G$2:$G$400, 'Action-Based Data'!$A6) -> 0 | J6: =SUMIFS(ALLData!$M$2:$M$400, ALLData!$B$2:$B$400, 'Action-Based Data'!J$1, ALLData!$G$2:$G$400, 'Action-Based Data'!$A6) -> 0 | ... Q6: =SUMIFS(ALLData!$M$2:$M$400, ALLData!$B$2:$B$400, 'Action-Based Data'!Q$1, ALLData!$G$2:$G$400, 'Action-Based Data'!$A6) -> 45179
A7: GTSR | B7: Global Terrosim Sanctions | C7: =SUMIFS(ALLData!$M$2:$M$400, ALLData!$B$2:$B$400, 'Action-Based Data'!C$1, ALLData!$G$2:$G$400, 'Action-Based Data'!$A7) -> 0 | D7: =SUMIFS(ALLData!$M$2:$M$400, ALLData!$B$2:$B$400, 'Action-Based Data'!D$1, ALLData!$G$2:$G$400, 'Action-Based Data'!$A7) -> 0 | E7: =SUMIFS(ALLData!$M$2:$M$400, ALLData!$B$2:$B$400, 'Action-Based Data'!E$1, ALLData!$G$2:$G$400, 'Action-Based Data'!$A7) -> 0 | F7: =SUMIFS(ALLData!$M$2:$M$400, ALLData!$B$2:$B$400, 'Action-Based Data'!F$1, ALLData!$G$2:$G$400, 'Action-Based Data'!$A7) -> 49827.28 | G7: =SUMIFS(ALLData!$M$2:$M$400, ALLData!$B$2:$B$400, 'Action-Based Data'!G$1, ALLData!$G$2:$G$400, 'Action-Based Data'!$A7) -> 1730243.2 | H7: =SUMIFS(ALLData!$M$2:$M$400, ALLData!$B$2:$B$400, 'Action-Based Data'!H$1, ALLData!$G$2:$G$400, 'Action-Based Data'!$A7) -> 0 | I7: =SUMIFS(ALLData!$M$2:$M$400, ALLData!$B$2:$B$400, 'Action-Based Data'!I$1, ALLData!$G$2:$G$400, 'Action-Based Data'!$A7) -> 0 | J7: =SUMIFS(ALLData!$M$2:$M$400, ALLData!$B$2:$B$400, 'Action-Based Data'!J$1, ALLData!$G$2:$G$400, 'Action-Based Data'!$A7) -> 0 | ... Q7: =SUMIFS(ALLData!$M$2:$M$400, ALLData!$B$2:$B$400, 'Action-Based Data'!Q$1, ALLData!$G$2:$G$400, 'Action-Based Data'!$A7) -> 0
A8: NTSR | B8: Narcotics Trafficking Sanctions | C8: =SUMIFS(ALLData!$M$2:$M$400, ALLData!$B$2:$B$400, 'Action-Based Data'!C$1, ALLData!$G$2:$G$400, 'Action-Based Data'!$A8) -> 0 | D8: =SUMIFS(ALLData!$M$2:$M$400, ALLData!$B$2:$B$400, 'Action-Based Data'!D$1, ALLData!$G$2:$G$400, 'Action-Based Data'!$A8) -> 0 | E8: =SUMIFS(ALLData!$M$2:$M$400, ALLData!$B$2:$B$400, 'Action-Based Data'!E$1, ALLData!$G$2:$G$400, 'Action-Based Data'!$A8) -> 0 | F8: =SUMIFS(ALLData!$M$2:$M$400, ALLData!$B$2:$B$400, 'Action-Based Data'!F$1, ALLData!$G$2:$G$400, 'Action-Based Data'!$A8) -> 138798 | G8: =SUMIFS(ALLData!$M$2:$M$400, ALLData!$B$2:$B$400, 'Action-Based Data'!G$1, ALLData!$G$2:$G$400, 'Action-Based Data'!$A8) -> 83657.6 | H8: =SUMIFS(ALLData!$M$2:$M$400, ALLData!$B$2:$B$400, 'Action-Based Data'!H$1, ALLData!$G$2:$G$400, 'Action-Based Data'!$A8) -> 0 | I8: =SUMIFS(ALLData!$M$2:$M$400, ALLData!$B$2:$B$400, 'Action-Based Data'!I$1, ALLData!$G$2:$G$400, 'Action-Based Data'!$A8) -> 0 | J8: =SUMIFS(ALLData!$M$2:$M$400, ALLData!$B$2:$B$400, 'Action-Based Data'!J$1, ALLData!$G$2:$G$400, 'Action-Based Data'!$A8) -> 0 | ... Q8: =SUMIFS(ALLData!$M$2:$M$400, ALLData!$B$2:$B$400, 'Action-Based Data'!Q$1, ALLData!$G$2:$G$400, 'Action-Based Data'!$A8) -> 0
A9: TCO | B9: Transnational Criminal Organization Sanctions | C9: =SUMIFS(ALLData!$M$2:$M$400, ALLData!$B$2:$B$400, 'Action-Based Data'!C$1, ALLData!$G$2:$G$400, 'Action-Based Data'!$A9) -> 0 | D9: =SUMIFS(ALLData!$M$2:$M$400, ALLData!$B$2:$B$400, 'Action-Based Data'!D$1, ALLData!$G$2:$G$400, 'Action-Based Data'!$A9) -> 0 | E9: =SUMIFS(ALLData!$M$2:$M$400, ALLData!$B$2:$B$400, 'Action-Based Data'!E$1, ALLData!$G$2:$G$400, 'Action-Based Data'!$A9) -> 0 | F9: =SUMIFS(ALLData!$M$2:$M$400, ALLData!$B$2:$B$400, 'Action-Based Data'!F$1, ALLData!$G$2:$G$400, 'Action-Based Data'!$A9) -> 0 | G9: =SUMIFS(ALLData!$M$2:$M$400, ALLData!$B$2:$B$400, 'Action-Based Data'!G$1, ALLData!$G$2:$G$400, 'Action-Based Data'!$A9) -> 0 | H9: =SUMIFS(ALLData!$M$2:$M$400, ALLData!$B$2:$B$400, 'Action-Based Data'!H$1, ALLData!$G$2:$G$400, 'Action-Based Data'!$A9) -> 0 | I9: =SUMIFS(ALLData!$M$2:$M$400, ALLData!$B$2:$B$400, 'Action-Based Data'!I$1, ALLData!$G$2:$G$400, 'Action-Based Data'!$A9) -> 0 | J9: =SUMIFS(ALLData!$M$2:$M$400, ALLData!$B$2:$B$400, 'Action-Based Data'!J$1, ALLData!$G$2:$G$400, 'Action-Based Data'!$A9) -> 0 | ... Q9: =SUMIFS(ALLData!$M$2:$M$400, ALLData!$B$2:$B$400, 'Action-Based Data'!Q$1, ALLData!$G$2:$G$400, 'Action-Based Data'!$A9) -> 0
A10: WMDPSR | B10: Weapons of Mass Destruction Sanctions | C10: =SUMIFS(ALLData!$M$2:$M$400, ALLData!$B$2:$B$400, 'Action-Based Data'!C$1, ALLData!$G$2:$G$400, 'Action-Based Data'!$A10) -> 2270531.2 | D10: =SUMIFS(ALLData!$M$2:$M$400, ALLData!$B$2:$B$400, 'Action-Based Data'!D$1, ALLData!$G$2:$G$400, 'Action-Based Data'!$A10) -> 201000 | E10: =SUMIFS(ALLData!$M$2:$M$400, ALLData!$B$2:$B$400, 'Action-Based Data'!E$1, ALLData!$G$2:$G$400, 'Action-Based Data'!$A10) -> 20800 | F10: =SUMIFS(ALLData!$M$2:$M$400, ALLData!$B$2:$B$400, 'Action-Based Data'!F$1, ALLData!$G$2:$G$400, 'Action-Based Data'!$A10) -> 200004.62 | G10: =SUMIFS(ALLData!$M$2:$M$400, ALLData!$B$2:$B$400, 'Action-Based Data'!G$1, ALLData!$G$2:$G$400, 'Action-Based Data'!$A10) -> 52644897 | H10: =SUMIFS(ALLData!$M$2:$M$400, ALLData!$B$2:$B$400, 'Action-Based Data'!H$1, ALLData!$G$2:$G$400, 'Action-Based Data'!$A10) -> 0 | I10: =SUMIFS(ALLData!$M$2:$M$400, ALLData!$B$2:$B$400, 'Action-Based Data'!I$1, ALLData!$G$2:$G$400, 'Action-Based Data'!$A10) -> 39399.529 | J10: =SUMIFS(ALLData!$M$2:$M$400, ALLData!$B$2:$B$400, 'Action-Based Data'!J$1, ALLData!$G$2:$G$400, 'Action-Based Data'!$A10) -> 0 | ... Q10: =SUMIFS(ALLData!$M$2:$M$400, ALLData!$B$2:$B$400, 'Action-Based Data'!Q$1, ALLData!$G$2:$G$400, 'Action-Based Data'!$A10) -> 0
A12: Total | C12: =SUM(C4:C10) -> 2270531.2 | D12: =SUM(D4:D10) -> 201000 | E12: =SUM(E4:E10) -> 1979753.8 | F12: =SUM(F4:F10) -> 26299318 | G12: =SUM(G4:G10) -> 55122834 | H12: =SUM(H4:H10) -> 0 | I12: =SUM(I4:I10) -> 374199.53 | J12: =SUM(J4:J10) -> 0 | ... Q12: =SUM(Q4:Q10) -> 45179
A14: Note: OFAC's terminology for some of these action-based programs has shifted over time. CBO has generally maintained the original categorization, but for ease, the corresponding programs are linked above.

Sheet ALLData
A1: Date | B1: FY | C1: Violator | D1: Financial vs. Non-Financial? | E1: Years of violations | F1: All Sanctions Violated | G1: Individual Violations | H1: Base Penalty Per Type of Sanction | I1: Sum of Base Penalties | J1: Percent Assigned to Each Type | K1: Split Used | L1: Announced settlement amount | M1: Penalty Per Program
A2: 40574 | B2: 2011 | C2: Trans Pacific National Bank | D2: Financial | E2: 2007-2008 | F2: Iran | G2: Iran | H2: 50000 | I2: 50000 | J2: 1 | L2: 12500 | M2: 12500
A3: 40574 | B3: 2011 | C3: Aon International Energy | D3: Non-Financial | E3: 2005 | F3: Iran | G3: Iran | J3: 1 | L3: 36000 | M3: 36000
A4: 40640 | B4: 2011 | C4: Metropolitan Life Insurance Company | D4: Financial | E4: 2006 | F4: Cuba | G4: Cuba | H4: 50000 | I4: 50000 | J4: 1 | L4: 22500 | M4: 22500
A5: 40640 | B5: 2011 | C5: Aegis Electronic Group | D5: Non-Financial | E5: 2008-2009 | F5: Iran | G5: Iran | H5: 10000 | I5: 10000 | J5: 1 | L5: 20000 | M5: 20000
A6: 40640 | B6: 2011 | C6: McGriff, Seibels & Williams of Texas | D6: Financial | E6: 2004-2005 | F6: Iran | G6: Iran | J6: 1 | L6: 122408 | M6: 122408
A7: 40659 | B7: 2011 | C7: HCC Insurance Holdings | D7: Financial | E7: 2005-2006 | F7: Iran | G7: Iran | H7: 56960 | I7: 56960 | J7: 1 | L7: 38448 | M7: 38448
A8: 40659 | B8: 2011 | C8: Robbins Instruments | D8: Non-Financial | E8: 2005-2009 | F8: Iran | G8: Iran | H8: 103000 | I8: 103000 | J8: 1 | L8: 37080 | M8: 37080
A9: 40659 | B9: 2011 | C9: Individual from Houston, TX | D9: Non-Financial | E9: 2005 | F9: South Sudan | G9: South Sudan | H9: 250000 | I9: 250000 | J9: 1 | L9: 112500 | M9: 112500
A10: 40723 | B10: 2011 | C10: General Reinsurance | D10: Financial | E10: 2005 | F10: Iran | G10: Iran | H10: 131424 | I10: 131424 | J10: 1 | L10: 59130 | M10: 59130
A11: 40771 | B11: 2011 | C11: CMA CGM | D11: Non-Financial | E11: 2004-2009 | F11: Cuba, Iran, South Sudan | G11: Cuba | H11: =I11/3 -> 213333.33 | I11: 640000 | J11: =H11/I11 -> 0.33333333 | K11: Even | L11: 374400 | M11: =L11*J11 -> 124800
A12: 40771 | B12: 2011 | C12: CMA CGM | D12: Non-Financial | E12: 2004-2010 | F12: Cuba, Iran, South Sudan | G12: Iran | H12: =I12/3 -> 213333.33 | I12: 640000 | J12: =H12/I12 -> 0.33333333 | K12: Even | L12: 374400 | M12: =L12*J12 -> 124800
A13: 40771 | B13: 2011 | C13: CMA CGM | D13: Non-Financial | E13: 2004-2011 | F13: Cuba, Iran, South Sudan | G13: South Sudan | H13: =I13/3 -> 213333.33 | I13: 640000 | J13: =H13/I13 -> 0.33333333 | K13: Even | L13: 374400 | M13: =L13*J13 -> 124800
A14: 40771 | B14: 2011 | C14: Norton Lilly | D14: Non-Financial | E14: 2006 | F14: Iran | G14: Iran | H14: 25000 | I14: 25000 | J14: 1
A15: 40771 | B15: 2011 | C15: Societe Generale New York Branch | D15: Non-Financial | E15: 2006-2007 | F15: Iran | G15: Iran | H15: 164977 | I15: 164977 | J15: 1 | L15: 111359 | M15: 111359
A16: 40771 | B16: 2011 | C16: Heritage Turbines | D16: Non-Financial | E16: 2007 | F16: South Sudan | G16: South Sudan | H16: 10000 | I16: 10000 | J16: 1 | L16: 4500 | M16: 4500
A17: 40780 | B17: 2011 | C17: JPMorgan Chase | D17: Financial | E17: 2005-2011 | F17: Cuba | G17: Cuba | H17: 111215000 | I17: 114406838 | J17: =1-J18 -> 0.97428617 | K17: Penalty Ratio | L17: 88300000 | M17: =L17*J17 -> 86029469
A18: 40780 | B18: 2011 | C18: JPMorgan Chase | D18: Financial | E18: 2005-2013 | F18: WMDPSR | G18: WMDPSR | H18: 2941838 | I18: 114406838 | J18: =H18/I18 -> 0.02571383 | K18: Penalty Ratio | L18: 88300000 | M18: =L18*J18 -> 2270531.2
A19: 40816 | B19: 2011 | C19: Flowserve | D19: Non-Financial | E19: 2005-2006 | F19: Iran, South Sudan, Cuba | G19: Iran | H19: =I19/3 -> 220351 | I19: 661053 | J19: =H19/I19 -> 0.33333333 | K19: Even | L19: 502408 | M19: =L19*J19 -> 167469.33
A20: 40816 | B20: 2011 | C20: Flowserve | D20: Non-Financial | E20: 2005-2006 | F20: Iran, South Sudan, Cuba | G20: South Sudan | H20: =I20/3 -> 220351 | I20: 661053 | J20: =H20/I20 -> 0.33333333 | K20: Even | L20: 502408 | M20: =L20*J20 -> 167469.33
A21: 40816 | B21: 2011 | C21: Flowserve | D21: Non-Financial | E21: 2005-2006 | F21: Iran, South Sudan, Cuba | G21: Cuba | H21: =I21/3 -> 220351 | I21: 661053 | J21: =H21/I21 -> 0.33333333 | K21: Even | L21: 502408 | M21: =L21*J21 -> 167469.33
A22: 40830 | B22: 2012 | C22: Sunrise Technologies and Trading | D22: Non-Financial | E22: 2007-2011 | F22: Iran | G22: Iran | J22: 1 | L22: 1661672 | M22: 1661672
A23: 40843 | B23: 2012 | C23: Zurigo Trading | D23: Non-Financial | E23: 2006 | F23: Iran | G23: Iran | H23: 10000 | I23: 10000 | J23: 1
A24: 40855 | B24: 2012 | C24: Wilson Tool International | D24: Non-Financial | E24: 2005 | F24: Iran | G24: Iran | H24: 25000 | I24: 25000 | J24: 1 | L24: 15000 | M24: 15000
A25: 40855 | B25: 2012 | C25: ASF | D25: Non-Financial | E25: 2006 | F25: Iran | G25: Iran | H25: 10000 | I25: 10000 | J25: 1 | L25: 5400 | M25: 5400
A26: 40876 | B26: 2012 | C26: Commerzbank AG, NY Branch | D26: Financial | E26: 2005 | F26: Cuba | G26: Cuba | H26: 260000 | I26: 260000 | J26: 1 | L26: 175500 | M26: 175500
A27: 40897 | B27: 2012 | C27: Lanier Marine Liquidators | D27: Non-Financial | E27: 2005-2006 | F27: South Sudan | G27: South Sudan | H27: 50000 | I27: 50000 | J27: 1 | L27: 13500 | M27: 13500
A28: 40946 | B28: 2012 | C28: Teledyne Technologies | D28: Non-Financial | E28: 2007 | F28: South Sudan | G28: South Sudan | H28: 61383 | I28: 61383 | J28: 1 | L28: 30385 | M28: 30385
A29: 40960 | B29: 2012 | C29: Richland Trace Homeowners | D29: Non-Financial | E29: 2005-2009 | F29: Liberia | G29: Liberia | H29: 10000 | I29: 10000 | J29: 1
A30: 40963 | B30: 2012 | C30: Online Micro | D30: Non-Financial | E30: 2009-2010 | F30: Iran | G30: Iran | J30: 1 | L30: 1054388 | M30: 1054388
A31: 41009 | B31: 2012 | C31: Essie Cosmetics and former Individual Corporate Office | D31: Non-Financial | E31: 2009-2010 | F31: Iran | G31: Iran | H31: 750000 | I31: 750000 | J31: 1 | L31: 450000 | M31: 450000
A32: 41024 | B32: 2012 | C32: Sandhill Scientific | D32: Non-Financial | E32: 2007-2008 | F32: Iran | G32: Iran | I32: 290000 | J32: 1 | L32: 126000 | M32: 126000
A33: 41050 | B33: 2012 | C33: Genesis Asset Managers | D33: Financial | E33: 2007 | F33: Iran | G33: Iran | J33: 1 | L33: 112500 | M33: 112500
A34: 41072 | B34: 2012 | C34: ING Bank | D34: Financial | E34: 2002-2007 | F34: Cuba, Burma, South Sudan, Libya, Iran | G34: Cuba | H34: 636450000 | I34: 665992444 | J34: =H34/I34 -> 0.95564147 | K34: Penalty Ratio | L34: 619000000 | M34: =J34*L34 -> 5.9154207e+08
A35: 41072 | B35: 2012 | C35: ING Bank | D35: Financial | E35: 2002-2007 | F35: Cuba, Burma, South Sudan, Libya, Iran | G35: Burma | H35: 19919545 | I35: 665992444 | J35: =H35/I35 -> 0.029909566 | K35: Penalty Ratio | L35: 619000000 | M35: =J35*L35 -> 18514021
A36: 41072 | B36: 2012 | C36: ING Bank | D36: Financial | E36: 2002-2007 | F36: Cuba, Burma, South Sudan, Libya, Iran | G36: South Sudan | H36: 6531899 | I36: 665992444 | J36: =H36/I36 -> 0.0098077674 | K36: Penalty Ratio | L36: 619000000 | M36: =J36*L36 -> 6071008
A37: 41072 | B37: 2012 | C37: ING Bank | D37: Financial | E37: 2002-2007 | F37: Cuba, Burma, South Sudan, Libya, Iran | G37: Libya | H37: 375000 | I37: 665992444 | J37: =H37/I37 -> 0.00056306945 | K37: Penalty Ratio | L37: 619000000 | M37: =J37*L37 -> 348539.99
A38: 41072 | B38: 2012 | C38: ING Bank | D38: Financial | E38: 2002-2007 | F38: Cuba, Burma, South Sudan, Libya, Iran | G38: Iran | H38: 2716000 | I38: 665992444 | J38: =H38/I38 -> 0.0040781243 | K38: Penalty Ratio | L38: 619000000 | M38: =J38*L38 -> 2524359
A39: 41074 | B39: 2012 | C39: National Bank of Abu Dhabi | D39: Financial | E39: 2004-2005 | F39: South Sudan | G39: South Sudan | H39: 4276000 | I39: 4276000 | J39: 1 | L39: 855000 | M39: 855000
A40: 41100 | B40: 2012 | C40: Great Western Malting | D40: Non-Financial | E40: 2006-2009 | F40: Cuba | G40: Cuba | H40: 5990000 | I40: 5990000 | J40: 1 | L40: 1347750 | M40: 1347750
A41: 41143 | B41: 2012 | C41: Grand Resources USA | D41: Non-Financial | E41: 2005-2009 | F41: Iran, WMDPSR | G41: Iran | H41: =I41/2 -> 335000 | I41: 670000 | J41: =H41/I41 -> 0.5 | K41: Even | L41: 402000 | M41: =L42*J41 -> 201000
A42: 41143 | B42: 2012 | C42: Grand Resources USA | D42: Non-Financial | E42: 2005-2009 | F42: Iran, WMDPSR | G42: WMDPSR | H42: =I42/2 -> 335000 | I42: 670000 | J42: =H42/I42 -> 0.5 | K42: Even | L42: 402000 | M42: =L42*J42 -> 201000
A43: 41201 | B43: 2013 | C43: Brasseler USA | D43: Non-Financial | E43: 2006-2009 | F43: Iran | G43: Iran | H43: 21000 | I43: 21000 | J43: 1 | L43: 18900 | M43: 18900
A44: 41228 | B44: 2013 | C44: Natoli Engineering Company | D44: Non-Financial | E44: 2008-2010 | F44: Foreign Narcotics | G44: FNKSR | H44: 98000 | I44: 98000 | J44: 1 | L44: 52920 | M44: 52920
A45: 41228 | B45: 2013 | C45: Sogda Limited | D45: Non-Financial | E45: 2009-2010 | F45: Iran | G45: Iran | H45: 570000 | I45: 570000 | J45: 1 | L45: 128250 | M45: 128250
A46: 41253 | B46: 2013 | C46: Standard Charter Bank | D46: Financial | E46: 2001-2011 | F46: Burma, Iran, Libya, South Sudan, Foreign Narcotics | G46: Burma | H46: 625000 | I46: 209747769 | J46: =H46/I46 -> 0.0029797695 | K46: Penalty Ratio | L46: 132000000 | M46: =J46*L46 -> 393329.57
A47: 41253 | B47: 2013 | C47: Standard Charter Bank | D47: Financial | E47: 2001-2011 | F47: Burma, Iran, Libya, South Sudan, Foreign Narcotics | G47: Iran | H47: 74553945 | I47: 209747769 | J47: =H47/I47 -> 0.35544571 | K47: Penalty Ratio | L47: 132000000 | M47: =J47*L47 -> 46918834
A48: 41253 | B48: 2013 | C48: Standard Charter Bank | D48: Financial | E48: 2001-2011 | F48: Burma, Iran, Libya, South Sudan, Foreign Narcotics | G48: Libya | H48: 25127006 | I48: 209747769 | J48: =H48/I48 -> 0.1197963 | K48: Penalty Ratio | L48: 132000000 | M48: =J48*L48 -> 15813111
A49: 41253 | B49: 2013 | C49: Standard Charter Bank | D49: Financial | E49: 2001-2011 | F49: Burma, Iran, Libya, South Sudan, Foreign Narcotics | G49: South Sudan | H49: 109320066 | I49: 209747769 | J49: =H49/I49 -> 0.52119775 | K49: Penalty Ratio | L49: 132000000 | M49: =J49*L49 -> 68798103
A50: 41253 | B50: 2013 | C50: Standard Charter Bank | D50: Financial | E50: 2001-2011 | F50: Burma, Iran, Libya, South Sudan, Foreign Narcotics | G50: FNKSR | H50: 121753 | I50: 209747769 | J50: =H50/I50 -> 0.0005804734 | K50: Penalty Ratio | L50: 132000000 | M50: =J50*L50 -> 76622.488
A51: 41254 | B51: 2013 | C51: HSBC Holdings | D51: Financial | E51: 2004-2010 | F51: Cuba, Burma, South Sudan, Libya, Iran | G51: Cuba | H51: 2600000 | I51: 1159872734 | J51: =H51/I51 -> 0.0022416252 | K51: Penalty Ratio | L51: 375000000 | M51: =J51*L51 -> 840609.47
A52: 41254 | B52: 2013 | C52: HSBC Holdings | D52: Financial | E52: 2004-2010 | F52: Cuba, Burma, South Sudan, Libya, Iran | G52: Burma | H52: 416346763 | I52: 1159872734 | J52: =H52/I52 -> 0.35895901 | K52: Penalty Ratio | L52: 375000000 | M52: =J52*L52 -> 1.3460963e+08
A53: 41254 | B53: 2013 | C53: HSBC Holdings | D53: Financial | E53: 2004-2010 | F53: Cuba, Burma, South Sudan, Libya, Iran | G53: South Sudan | H53: 378554375 | I53: 1159872734 | J53: =H53/I53 -> 0.32637579 | K53: Penalty Ratio | L53: 375000000 | M53: =J53*L53 -> 1.2239092e+08
A54: 41254 | B54: 2013 | C54: HSBC Holdings | D54: Financial | E54: 2004-2010 | F54: Cuba, Burma, South Sudan, Libya, Iran | G54: Libya | H54: 6997304 | I54: 1159872734 | J54: =H54/I54 -> 0.0060328205 | K54: Penalty Ratio | L54: 375000000 | M54: =J54*L54 -> 2262307.7
A55: 41254 | B55: 2013 | C55: HSBC Holdings | D55: Financial | E55: 2004-2010 | F55: Cuba, Burma, South Sudan, Libya, Iran | G55: Iran | H55: 355374292 | I55: 1159872734 | J55: =H55/I55 -> 0.30639076 | K55: Penalty Ratio | L55: 375000000 | M55: =J55*L55 -> 1.1489654e+08
A56: 41255 | B56: 2013 | C56: Bank of Tokyo -- Mitsubishi | D56: Financial | E56: 2006-2007 | F56: WMD, Burma, Iran, Cuba, South Sudan | G56: EO 13382 | H56: na | I56: na | J56: 0.2 | K56: Even | L56: 8571634 | M56: =J56*L56 -> 1714326.8
A57: 41255 | B57: 2013 | C57: Bank of Tokyo -- Mitsubishi | D57: Financial | E57: 2006-2007 | F57: WMD, Burma, Iran, Cuba, South Sudan | G57: Burma | H57: na | I57: na | J57: 0.2 | K57: Even | L57: 8571634 | M57: =J57*L57 -> 1714326.8
A58: 41255 | B58: 2013 | C58: Bank of Tokyo -- Mitsubishi | D58: Financial | E58: 2006-2007 | F58: WMD, Burma, Iran, Cuba, South Sudan | G58: Iran | H58: na | I58: na | J58: 0.2 | K58: Even | L58: 8571634 | M58: =J58*L58 -> 1714326.8
A59: 41255 | B59: 2013 | C59: Bank of Tokyo -- Mitsubishi | D59: Financial | E59: 2006-2007 | F59: WMD, Burma, Iran, Cuba, South Sudan | G59: Cuba | H59: na | I59: na | J59: 0.2 | K59: Even | L59: 8571634 | M59: =J59*L59 -> 1714326.8
A60: 41255 | B60: 2013 | C60: Bank of Tokyo -- Mitsubishi | D60: Financial | E60: 2006-2007 | F60: WMD, Burma, Iran, Cuba, South Sudan | G60: South Sudan | H60: na | I60: na | J60: 0.2 | K60: Even | L60: 8571634 | M60: =J60*L60 -> 1714326.8
A61: 41276 | B61: 2013 | C61: Ellman International | D61: Non-Financial | E61: 2005-2008 | F61: Iran | G61: Iran | H61: 426000 | I61: 426000 | J61: 1 | L61: 191700 | M61: 191700
A62: 41292 | B62: 2013 | C62: Dal-Tech Devices | D62: Non-Financial | E62: ? | F62: Iran | G62: Iran | H62: 500000 | I62: 500000 | J62: 1 | L62: 10000 | M62: 10000
A63: 41306 | B63: 2013 | C63: Offsore Marine Laboratories | D63: Non-Financial | E63: 2007-2008 | F63: Iran | G63: Iran | H63: =I63*J63 -> 83500 | I63: 167000 | J63: 0.5 | K63: Even | L63: 97695 | M63: =J63*L63 -> 48847.5
A64: 41306 | B64: 2013 | C64: Offsore Marine Laboratories | D64: Non-Financial | E64: 2007-2008 | F64: WMD EO | G64: EO 13382 | H64: =I64*J64 -> 83500 | I64: 167000 | J64: 0.5 | K64: Even | L64: 97695 | M64: =J64*L64 -> 48847.5
A65: 41326 | B65: 2013 | C65: American Optisurgical | D65: Non-Financial | E65: 2007-2008 | F65: Iran | G65: Iran | H65: =I65*J65 -> 449000 | I65: 449000 | J65: 1 | L65: 404100 | M65: =L65*J65 -> 404100
A66: 41327 | B66: 2013 | C66: Tung Tai Group | D66: Non-Financial | E66: 2010 | F66: Cuba | G66: Cuba | H66: 65000 | I66: 65000 | J66: 1 | L66: 43875 | M66: 43875
A67: 41327 | B67: 2013 | C67: Bank of Guam | D67: Financial | E67: 2010 | F67: Iran | G67: Iran | H67: 20000 | I67: 20000 | J67: 1 | L67: 27000 | M67: 27000
A68: 41338 | B68: 2013 | C68: EGL | D68: Non-Financial | E68: 2005-2008 | F68: Cuba, Iran | G68: Cuba | H68: =I68*J68 -> 103444.5 | I68: 206889 | J68: 0.5 | K68: Even | L68: 139650 | M68: =L68*J68 -> 69825
A69: 41338 | B69: 2013 | C69: EGL | D69: Non-Financial | E69: 2005-2008 | F69: Cuba, Iran | G69: Iran | H69: =I69*J69 -> 103444.5 | I69: 206889 | J69: 0.5 | K69: Even | L69: 139650 | M69: =L69*J69 -> 69825
A70: 41354 | B70: 2013 | C70: Maritech Commercial | D70: Non-Financial | E70: 2009-10 | F70: WMDPSR (not EO) | G70: WMDPSR | H70: 32000 | I70: 32000 | J70: 1 | L70: 20800 | M70: =J70*L70 -> 20800
A71: 41376 | B71: 2013 | C71: SAN Corporation | D71: Non-Financial | E71: 2007 | F71: Iran | G71: Iran | H71: 25000 | I71: 25000 | J71: 1 | L71: 22500 | M71: 22500
A72: 41389 | B72: 2013 | C72: Toyota Motor Credit Corporation | D72: Financial | E72: 2008-2010 | F72: Foreign Narcotics | G72: FNKSR | H72: 26000 | I72: 26000 | J72: 1 | L72: 23400 | M72: 23400
A73: 41403 | B73: 2013 | C73: The American Steamship Owners Mutual Protection and Indemnity Association | D73: Financial | E73: 2003-2007 | F73: Cuba, South Sudan, Iran | G73: Cuba | H73: 61000 | I73: 1729000 | J73: =H73/I73 -> 0.035280509 | K73: Penalty Ratio | L73: 348000 | M73: =J73*L73 -> 12277.617
A74: 41403 | B74: 2013 | C74: The American Steamship Owners Mutual Protection and Indemnity Association | D74: Financial | E74: 2003-2007 | F74: Cuba, South Sudan, Iran | G74: South Sudan | H74: 844000 | I74: 1729000 | J74: =H74/I74 -> 0.48814344 | K74: Penalty Ratio | L74: 348000 | M74: =J74*L74 -> 169873.92
A75: 41403 | B75: 2013 | C75: The American Steamship Owners Mutual Protection and Indemnity Association | D75: Financial | E75: 2003-2007 | F75: Cuba, South Sudan, Iran | G75: Iran | H75: 824000 | I75: 1729000 | J75: =H75/I75 -> 0.47657606 | K75: Penalty Ratio | L75: 348000 | M75: =J75*L75 -> 165848.47
A76: 41437 | B76: 2013 | C76: ATP Tour | D76: Non-Financial | E76: 2007-2010 | F76: Iran | G76: Iran | H76: 135000 | I76: 135000 | J76: 1 | L76: 48600 | M76: 48600
A77: 41452 | B77: 2013 | C77: Wells Fargo Bank | D77: Financial | E77: 2007-2010 | F77: Foreign Narcotics | G77: FNKSR | H77: 37996 | I77: 37996 | J77: 1 | L77: 23937 | M77: 23937
A78: 41453 | B78: 2013 | C78: Intesa Sanpaolo | D78: Financial | E78: 2004-2008 | F78: Cuba, South Sudan, Iran | G78: Cuba | H78: 1867000 | I78: 9362000 | J78: =H78/I78 -> 0.1994232 | K78: Penalty Ratio | L78: 2949030 | M78: =J78*L78 -> 588105
A79: 41453 | B79: 2013 | C79: Intesa Sanpaolo | D79: Financial | E79: 2004-2008 | F79: Cuba, South Sudan, Iran | G79: South Sudan | H79: 3371000 | I79: 9362000 | J79: =H79/I79 -> 0.36007263 | K79: Penalty Ratio | L79: 2949030 | M79: =J79*L79 -> 1061865
A80: 41453 | B80: 2013 | C80: Intesa Sanpaolo | D80: Financial | E80: 2004-2008 | F80: Cuba, South Sudan, Iran | G80: Iran | H80: 4124000 | I80: 9362000 | J80: =H80/I80 -> 0.44050417 | K80: Penalty Ratio | L80: 2949030 | M80: =J80*L80 -> 1299060
A81: 41474 | B81: 2013 | C81: Stanley Drilling Equipment & Supply | D81: Non-Financial | E81: 2008 | F81: Iran | G81: Iran | H81: 156000 | I81: 156000 | J81: 1 | L81: 84240 | M81: 84240
A82: 41477 | B82: 2013 | C82: American Express Travel Related Services | D82: Non-Financial | E82: 2005-2011 | F82: Cuba | G82: Cuba | H82: 3629250 | I82: 3629250 | J82: 1 | L82: 5226120 | M82: 5226120
A83: 41522 | B83: 2013 | C83: Deutsche Bank | D83: Financial | E83: 2008, 2009 | F83: WMD (EO 13382) | G83: EO 13382 | H83: 35000 | I83: 35000 | J83: 1 | L83: 18900 | M83: =J83*L83 -> 18900
A84: 41523 | B84: 2013 | C84: Communications and Power Industries | D84: Non-Financial | E84: 2006-2010 | F84: Iran | G84: Iran | H84: 1100096 | I84: 1100096 | J84: 1 | L84: 346530 | M84: 346530
A85: 41526 | B85: 2013 | C85: World Fuel Services | D85: Non-Financial | E85: 2007-2009 | F85: Iran, South Sudan, Cuba | G85: Iran | H85: =I85/3 -> 24383.667 | I85: 73151 | J85: =H85/I85 -> 0.33333333 | K85: Even | L85: 39501 | M85: =L85*J85 -> 13167
A86: 41526 | B86: 2013 | C86: World Fuel Services | D86: Non-Financial | E86: 2007-2009 | F86: Iran, South Sudan, Cuba | G86: South Sudan | H86: =I86/3 -> 24383.667 | I86: 73151 | J86: =H86/I86 -> 0.33333333 | K86: Even | L86: 39501 | M86: =L86*J86 -> 13167
A87: 41526 | B87: 2013 | C87: World Fuel Services | D87: Non-Financial | E87: 2007-2009 | F87: Iran, South Sudan, Cuba | G87: Cuba | H87: =I87/3 -> 24383.667 | I87: 73151 | J87: =H87/I87 -> 0.33333333 | K87: Even | L87: 39501 | M87: =L87*J87 -> 13167
A88: 41543 | B88: 2013 | C88: Finans | D88: Financial | E88: 2012 | F88: Iran | G88: Iran | H88: 750000 | I88: 750000 | J88: 1
A89: 41568 | B89: 2014 | C89: Alma Investment LLC | D89: Financial | E89: 2009-2010 | F89: Iran | G89: Iran | H89: 1500000 | I89: 1500000 | J89: 1
A90: 41571 | B90: 2014 | C90: Ameron International Corporation | D90: Non-Financial | E90: 2005-2006 | F90: Iran, Cuba | G90: Iran | H90: =I90*J90 -> 345000 | I90: 690000 | J90: 0.5 | K90: Even | L90: 434700 | M90: =L90*J90 -> 217350
A91: 41571 | B91: 2014 | C91: Ameron International Corporation | D91: Non-Financial | E91: 2005-2006 | F91: Iran, Cuba | G91: Cuba | H91: =I91*J91 -> 345000 | I91: 690000 | J91: 0.5 | K91: Even | L91: 434700 | M91: =L91*J91 -> 217350
A92: 41572 | B92: 2014 | C92: KMT Group | D92: Non-Financial | E92: 2009 | F92: Iran | G92: Iran | H92: 500000 | I92: 500000 | J92: 1 | L92: 125000 | M92: 125000
A93: 41604 | B93: 2014 | C93: Weatherford International | D93: Non-Financial | E93: 2003-2008 | F93: Cuba, Iran, South Sudan | G93: Cuba | H93: =I93*J93 -> 80135403 | I93: 107089941 | J93: 0.7483 | K93: Transaction Ratio | L93: 91026450 | M93: =L93*J93 -> 68115093
A94: 41604 | B94: 2014 | C94: Weatherford International | D94: Non-Financial | E94: 2003-2008 | F94: Cuba, Iran, South Sudan | G94: Iran | H94: =I94*J94 -> 26611850 | I94: 107089941 | J94: 0.2485 | K94: Transaction Ratio | L94: 91026450 | M94: =L94*J94 -> 22620073
A95: 41604 | B95: 2014 | C95: Weatherford International | D95: Non-Financial | E95: 2003-2008 | F95: Cuba, Iran, South Sudan | G95: South Sudan | H95: =I95*J95 -> 342687.81 | I95: 107089941 | J95: 0.0032 | K95: Transaction Ratio | L95: 91026450 | M95: =L95*J95 -> 291284.64
A96: 41611 | B96: 2014 | C96: Compass Bank | D96: Financial | E96: 2011 | F96: South Sudan | G96: South Sudan | H96: 25000 | I96: 25000 | J96: =H96/I96 -> 1 | L96: 19125 | M96: 19125
A97: 41619 | B97: 2014 | C97: The Royal Bank of Scotland | D97: Financial | E97: 2005-2009 | F97: Cuba, Burma, South Sudan, Iran | G97: Cuba | H97: 780000 | I97: 66244614 | J97: =H97/I97 -> 0.011774542 | K97: Penalty Ratio | L97: 33122307 | M97: =J97*L97 -> 390000
A98: 41619 | B98: 2014 | C98: The Royal Bank of Scotland | D98: Financial | E98: 2005-2009 | F98: Cuba, Burma, South Sudan, Iran | G98: Burma | H98: 5769308 | I98: 66244614 | J98: =H98/I98 -> 0.087090975 | K98: Penalty Ratio | L98: 33122307 | M98: =J98*L98 -> 2884654
A99: 41619 | B99: 2014 | C99: The Royal Bank of Scotland | D99: Financial | E99: 2005-2009 | F99: Cuba, Burma, South Sudan, Iran | G99: South Sudan | H99: 54860306 | I99: 66244614 | J99: =H99/I99 -> 0.82814742 | K99: Penalty Ratio | L99: 33122307 | M99: =J99*L99 -> 27430153
A100: 41619 | B100: 2014 | C100: The Royal Bank of Scotland | D100: Financial | E100: 2005-2009 | F100: Cuba, Burma, South Sudan, Iran | G100: Iran | H100: 4835000 | I100: 66244614 | J100: =H100/I100 -> 0.072987066 | K100: Penalty Ratio | L100: 33122307 | M100: =J100*L100 -> 2417500
...

Sheet License
